{
  "metadata": {
    "total_count": 28,
    "export_date": "2025-11-16T10:47:57.788231",
    "version": "1.0",
    "description": "청년 정책 데이터 (FinKuRN)"
  },
  "policies": [
    {
      "id": 1,
      "policy_name": "청년내일로 교통패스",
      "filename": "청년내일로교통패스_2024.pdf",
      "policy_number": "POLICY-2024-001",
      "region": "서울",
      "category": "교통",
      "deadline": "2025-11-30",
      "summary": "만 19세~34세 청년에게 대중교통 이용 혜택을 제공하는 정책입니다.",
      "full_text": "청년내일로 교통패스는 청년들의 교통비 부담을 줄이기 위한 정책입니다...",
      "operation_period": null,
      "application_period": null,
      "support_content": null,
      "support_scale": null,
      "eligibility": {},
      "application_info": {},
      "additional_info": {},
      "required_documents": [],
      "created_at": "2025-11-16T01:20:22.805951",
      "updated_at": "2025-11-16T01:20:22.805951"
    },
    {
      "id": 2,
      "policy_name": "청년전세보증금 반환보증 지원",
      "filename": "청년전세보증금_2024.pdf",
      "policy_number": "POLICY-2024-002",
      "region": "전국",
      "category": "주거",
      "deadline": "2025-12-15",
      "summary": "청년 전세보증금 반환보증 지원 정책입니다.",
      "full_text": "청년들의 전세보증금 반환 보증을 지원하여 주거 안정을 돕는 정책입니다...",
      "operation_period": null,
      "application_period": null,
      "support_content": null,
      "support_scale": null,
      "eligibility": {},
      "application_info": {},
      "additional_info": {},
      "required_documents": [
        {
          "id": 1,
          "name": "주민등록등본",
          "notes": null,
          "description": "최근 1개월 이내 발급",
          "is_required": true,
          "issue_location": "주민센터 또는 정부24"
        },
        {
          "id": 2,
          "name": "임대차계약서 사본",
          "notes": "확정일자 날인 필요",
          "description": null,
          "is_required": true,
          "issue_location": "계약서 원본"
        },
        {
          "id": 3,
          "name": "소득증명서",
          "notes": null,
          "description": "최근 3개월",
          "is_required": true,
          "issue_location": "국세청 홈택스"
        },
        {
          "id": 4,
          "name": "통장사본",
          "notes": null,
          "description": null,
          "is_required": true,
          "issue_location": "해당 은행"
        }
      ],
      "created_at": "2025-11-16T01:20:22.809591",
      "updated_at": "2025-11-16T01:20:22.809591"
    },
    {
      "id": 3,
      "policy_name": "서울청년수당",
      "filename": "서울청년수당_2024.pdf",
      "policy_number": "POLICY-2024-003",
      "region": "서울",
      "category": "금융",
      "deadline": "2025-11-25",
      "summary": "서울시 거주 청년에게 구직활동비를 지원하는 정책입니다.",
      "full_text": "서울시에 거주하는 청년들의 구직활동을 지원하기 위한 정책입니다...",
      "operation_period": null,
      "application_period": null,
      "support_content": null,
      "support_scale": null,
      "eligibility": {},
      "application_info": {},
      "additional_info": {},
      "required_documents": [
        {
          "id": 1,
          "name": "신분증",
          "notes": null,
          "description": "주민등록증 또는 운전면허증",
          "is_required": true,
          "issue_location": "주민센터 또는 경찰서"
        },
        {
          "id": 2,
          "name": "주민등록등본",
          "notes": "서울시 거주 확인용",
          "description": "최근 1개월 이내",
          "is_required": true,
          "issue_location": "주민센터"
        },
        {
          "id": 3,
          "name": "소득증명서",
          "notes": "중위소득 150% 이하 확인",
          "description": "가구 소득 확인용",
          "is_required": true,
          "issue_location": "국세청 홈택스"
        }
      ],
      "created_at": "2025-11-16T01:20:22.810493",
      "updated_at": "2025-11-16T01:20:22.810493"
    },
    {
      "id": 4,
      "policy_name": "국민취업지원제도",
      "filename": "국민취업지원제도_2024.pdf",
      "policy_number": "POLICY-2024-004",
      "region": "전국",
      "category": "취업",
      "deadline": "상시모집",
      "summary": "취업을 원하는 청년에게 맞춤형 취업지원 서비스를 제공합니다.",
      "full_text": "국민취업지원제도는 취업 취약계층에게 종합적인 취업지원 서비스를 제공합니다...",
      "operation_period": null,
      "application_period": null,
      "support_content": null,
      "support_scale": null,
      "eligibility": {},
      "application_info": {},
      "additional_info": {},
      "required_documents": [
        {
          "id": 1,
          "name": "신분증",
          "notes": null,
          "description": null,
          "is_required": true,
          "issue_location": "주민센터"
        },
        {
          "id": 2,
          "name": "구직등록 확인서",
          "notes": "고용센터 방문 필수",
          "description": null,
          "is_required": true,
          "issue_location": "고용센터"
        },
        {
          "id": 3,
          "name": "소득·재산 확인 서류",
          "notes": null,
          "description": "가구 단위",
          "is_required": true,
          "issue_location": "국세청, 건강보험공단"
        },
        {
          "id": 4,
          "name": "통장사본",
          "notes": null,
          "description": "본인 명의",
          "is_required": true,
          "issue_location": "은행"
        }
      ],
      "created_at": "2025-11-16T01:20:22.811117",
      "updated_at": "2025-11-16T01:20:22.811117"
    },
    {
      "id": 5,
      "policy_name": "청년 창업지원 프로그램",
      "filename": "청년창업지원_2024.pdf",
      "policy_number": "POLICY-2024-005",
      "region": "전국",
      "category": "창업",
      "deadline": "2025-12-31",
      "summary": "창업을 준비하는 청년에게 자금과 교육을 지원합니다.",
      "full_text": "청년 창업가들을 위한 종합 지원 프로그램으로 자금, 멘토링, 공간을 제공합니다...",
      "operation_period": null,
      "application_period": null,
      "support_content": null,
      "support_scale": null,
      "eligibility": {},
      "application_info": {},
      "additional_info": {},
      "required_documents": [],
      "created_at": "2025-11-16T01:20:22.811806",
      "updated_at": "2025-11-16T01:20:22.811806"
    },
    {
      "id": 6,
      "policy_name": "(국민연금) 실업크레딧 지원",
      "filename": "국민연금_실업크레딧_지원_2025021100",
      "policy_number": "20250211005400110419",
      "region": "전국",
      "category": "일자리",
      "deadline": "상시",
      "summary": "실업자의 노후소득 보장을 강화하기 위해 구직급여 수혜기간 동안 국민연금 보험료의 일부를 지원하고 그 기간을 연금 가입기간으로 산입하는 제도",
      "full_text": "전국\n일자리\n상시\n\n공유하기\n인쇄\n스크랩\n(국민연금) 실업크레딧 지원\n최종 수정일2025년 2월 25일\n스크랩 수72\n조회수3076\n태그\n#보조금\n실업자의 노후소득 보장을 강화하기 위해 구직급여 수혜기간 동안 국민연금 보험료의 일부를 지원하고 그 기간을 연금 가입기간으로 산입하는 제도\n\n한 눈에 보는 정책 요약\n한 눈에 보는 정책 요약 - 정책번호, 정책분야, 지원내용, 사업 운영 기간, 사업 신청기간, 지원 규모(명), 비고\n정책번호\n20250211005400110419\n정책분야\n일자리\n지원내용\n- 지원기간 : 구직급여 수급기간으로 하되, 1인 생애 최대 12개월 까지 지원\n- 지원금액 : 연금 보험료는 인정소득의 9퍼센트이며, 이중 국가 지원 보험료는 연금 보험료의 75퍼센트\n* 인정소득은 구직급여기초임금일액*에 30일을 곱하여 월액으로 환산한 값의 1/2이며, 상*하한선은 보건복지부 장관이 고시 : 구직급여기초임금일액 - 퇴직 전 3개월간 평균임금\n* 실직자 국민연금 보험료의 75퍼센트 지원(고용보험기금 25퍼센트, 일반회계 25퍼센트, 국민연금기금 25퍼센트 지원), 자부담 25퍼센트\n사업 운영 기간\n상시 연중\n사업 신청기간\n상시\n지원 규모(명)\n제한없음\n신청자격\n신청자격 - 연령, 거주지역, 소득, 학력, 전공, 취업상태, 특화분야, 추가사항, 참여제한 대상\n연령\n만 18세~만 60세\n거주지역\n전국\n소득\n무관\n학력\n제한없음\n전공\n제한없음\n취업상태\n기타\n특화분야\n제한없음\n추가사항\n참여제한 대상\n신청방법\n신청방법 - 신청절차, 심사 및 발표, 신청 사이트, 제출 서류\n신청절차\n- 1단계 고용센터 : 실업크레딧 제도안내\n- 2단계 신청자 : 보험료 지원금 신청\n- 3단계 연금공단 : 지원여부 확인, 결정\n- 4단계 연금공단 : 보험료 부과\n- 5단계 신청자 : 본인부담 보험료 납부\n- 6단계 연금공단 : 보험료 정산\n심사 및 발표\n신청 사이트\nhttp://www.moel.go.kr/policy/policyinfo/safety/list7.do\n제출 서류\n기타\n기타 - 기타 정보, 주관 기관, 운영 기관, 참고사이트1, 참고사이트2\n기타 정보\n주관 기관\n고용노동부\n운영 기관\n참고사이트 1\nhttps://www.moel.go.kr/index.do\n참고사이트 2\n정보 변경 내역\n정보 변경 내역 표로 변경일자, 변경 내용으로 구성되어있음\n변경일자\t변경 내용\n2025.02.25\t최종 수정일\n2025.02.11\t최초 등록일",
      "operation_period": "상시 연중",
      "application_period": "상시",
      "support_content": "- 지원기간 : 구직급여 수급기간으로 하되, 1인 생애 최대 12개월 까지 지원 - 지원금액 : 연금 보험료는 인정소득의 9퍼센트이며, 이중 국가 지원 보험료는 연금 보험료의 75퍼센트 * 인정소득은 구직급여기초임금일액*에 30일을 곱하여 월액으로 환산한 값의 1/2이며, 상*하한선은 보건복지부 장관이 고시 : 구직급여기초임금일액 - 퇴직 전 3개월간 평균임금 * 실직자 국민연금 보험료의 75퍼센트 지원(고용보험기금 25퍼센트, 일반회계 25퍼센트, 국민연금기금 25퍼센트 지원), 자부담 25퍼센트",
      "support_scale": null,
      "eligibility": {
        "age": {
          "max": 60,
          "min": 18,
          "description": "만 18세~만 60세"
        },
        "income": {
          "description": "무관"
        },
        "region": ["전국"]
      },
      "application_info": {
        "application_url": "https://www.moel.go.kr/index.do",
        "managing_agency": "고용노동부",
        "operating_agency": "참고사이트 1"
      },
      "additional_info": {},
      "required_documents": [],
      "created_at": "2025-11-16T01:38:41.885821",
      "updated_at": "2025-11-16T01:38:41.885821"
    },
    {
      "id": 7,
      "policy_name": "고용보험 미적용자 출산급여 지원",
      "filename": "고용보험_미적용자_출산급여_지원_2025012300",
      "policy_number": "20250123005400110386",
      "region": "전국",
      "category": "복지문화",
      "deadline": "상시",
      "summary": "소득활동을 하고 있으나 고용보험 미적용으로 고용보험의 '출산전후휴가급여'를 지원받지 못하는 출산여성에게 출산급여 지원을 통해 모성보호와 생계지원",
      "full_text": "전국\n복지문화\n상시\n\n공유하기\n인쇄\n스크랩\n고용보험 미적용자 출산급여 지원\n최종 수정일2025년 1월 23일\n스크랩 수4\n조회수736\n태그\n#출산\n소득활동을 하고 있으나 고용보험 미적용으로 고용보험의 '출산전후휴가급여'를 지원받지 못하는 출산여성에게 출산급여 지원을 통해 모성보호와 생계지원\n\n한 눈에 보는 정책 요약\n한 눈에 보는 정책 요약 - 정책번호, 정책분야, 지원내용, 사업 운영 기간, 사업 신청기간, 지원 규모(명), 비고\n정책번호\n20250123005400110386\n정책분야\n복지문화\n지원내용\n○ 고용보험 미적용자 출산급여\n- 총 150만원\n- 유산, 사산의 경우는 임신 기간에 따라 급여 수준 상이\n- 임신 기간 15주까지 : 30만원 / 16~21주 : 50만원 / 22~27주 : 100만원 / 28주 이상 : 150만원\n사업 운영 기간\n2025년 1월 1일 ~ 2025년 12월 31일\n사업 신청기간\n상시\n지원 규모(명)\n제한없음\n신청자격\n신청자격 - 연령, 거주지역, 소득, 학력, 전공, 취업상태, 특화분야, 추가사항, 참여제한 대상\n연령\n제한없음\n거주지역\n전국\n소득\n소득 활동 중\n학력\n제한없음\n전공\n제한없음\n취업상태\n제한없음\n특화분야\n제한없음\n추가사항\n○ 출산 전 18개월중 3개월 이상 소득활동이 확인되어야 합니다.\n\n○ 근로자\n- 1유형 : 출산전 30일 이상 고용보험에 가입하고 있고, 고용보험의 출산전후휴가급여 수급요건을 미충족*한 근로자\n· 출산전후휴가가 끝난 날 전까지 피보험 단위 기간이 통산하여 180일 이상\n- 2유형 : 고용보험법상 고용보험 적용제외 사업*의 근로자 및 적용제외 근로자**\n* 적용제외 사업: 농,임,어업 중 법인이 아닌 자가 상시 4명 이하의 근로자를 사용하는 사업, 총 공사금액이 2천만원 미만인 공사, 연면적 100㎡ 이하 건축물의 건축, 200㎡ 이하 건축물의 대수선 공사\n- 적용제외 사업의 입증 : 관련 업종이 명시된 사업자등록증 또는 공적 기관이 발급한 확인서(예시:농업경영체등록확인서, 축산업허가증, 어업 경영체등록확인서, 어업허가증, 임업 후계자 증서, 공사금액이 명시된 도급계약서 등)\n** 적용제외 근로자 : 소정 근로시간이 월 60시간 미만인 근로자(주 15시간 미만 포함)\n- 3유형 : 고용보험 미성립 사업장 소속의 고용보험 미가입 근로자(고용보험 가입 의무가 있는 사업장이지만 성립신고를 하지 않아, 소속 근로자 또한 피보험자격을 갖지 못한 경우)\n\n○ 1인 사업자\n- 출산일 현재 피고용인이 없는 단독ㆍ공동사업자. 다만, 예외적으로 출산일 이전 3개월 이후 보조인력을 채용한 경우 지원 가능\n* 공동사업자의 경우 명의ㆍ실질 모두 공동사업자인 경우에 한함\n*농림어업에 종사하는 출산여성이 부부 공동명의의 '경영체등록확인서'를 제출한 경우 지원대상으로 인정\n- 4유형 : 1인 사업자로서 출산일 전전년도~당해년도 사업에 대한 세금신고(부가세, 소득세)사실이 있는자\n* 부동산임대업은 제외(부동산 임대 관련한 소득활동은 불인정)\n- 5유형 : 1인사업자로 출산일 전전년도~당해년도 사업에 대한 세금신고 사실이 없는 자\n\n○ 그밖의 소득활동을 하는 여성\n- 6유형 : 사업자등록을 하지 않은 특수형채 근로자 및 자유계약자(프리랜서) 등\n* 특수형태 근로자(19개 직종) : 보험설계\n참여제한 대상\n신청방법\n신청방법 - 신청절차, 심사 및 발표, 신청 사이트, 제출 서류\n신청절차\n○ 방문 신청 또는 우편 : 고용센터\n○ 온라인 신청 : 고용24 홈페이지(www.work24.go.kr)\n○ 지급 결정 / 지급 : 신청 접수 후 14일 이내 지급(부지급) 결정 및 통지 / 본인 계좌로 지급 => 별도로 신청절차를 넣어서 표기\n심사 및 발표\n신청 사이트\nhttps://www.work24.go.kr/cm/main.do\n제출 서류\n○ 공통\n- 고용보험 미적용자 출산(유산,사산)급여 신청서\n- 출산 자녀가 등록된 주민등록표 등본(유산, 사산의 경우는 임신기간이 명시된 의료기관 진단서)\n- 출산 전 18개월 중 3개월 이상의 소득 활동한 증빙자료(사업 또는 노무 제공 입증자료 및 소득 발생 입증자료)\n- 일용직 근로자 및 고용보험 적용제외자(2유형)는 출산 전 3개월 중 10일 이상 근로한 사실을 입증하면 '출산일 현재 근로'하는 것으로 인정\n\n○ 2유형, 3유형 : 고용보험 미가입 확인서(소정양식, 사업주가 작성), 재직증명서, 급여이체내역(통장사본)\n\n○ 4유형\n- 사업자등록증\n- 출산한 해의 전전년도~당해년도 사업활동에 대한 세금신고 사실을 확인할 수 있는 서류(1건 이상)\n예) 부가가치세 과세표준증명원, 부가가치세면세사업자 수입금액증명, 소득금액증명원 또는 표준재무제표증명원\n\n○ 5유형 : 사업자등록증, 출산일 이전 18개월 중 3개월 이상 소득 발생 증빙자료(예:카드매출영수증, 매출세금계산서 등)\n\n○ 6유형\n- 소득활동 증빙자료 : 예)근로계약서, 도급계약서, 재직증명서, 경력증명서 등\n- 출산일 이전 18개월 중 3개월 이상 소득 발생 증빙자료 : 예)노무제공의 대가 입금내역, 소득세원천징수 내역 등\n* 과거에 근로자 또는 사업자 경력이 있더라도, 현재 6유형에서의 소득 발생 사실을 반드시 1건 이상 증빙\n기타\n기타 - 기타 정보, 주관 기관, 운영 기관, 참고사이트1, 참고사이트2\n기타 정보\n주관 기관\n고용노동부\n운영 기관\n참고사이트 1\nhttps://www.gov.kr/portal/rcvfvrSvc/dtlEx/149200000153?administOrgCd=ALL\n참고사이트 2\n정보 변경 내역\n정보 변경 내역 표로 변경일자, 변경 내용으로 구성되어있음\n변경일자\t변경 내용\n2025.01.23\t최종 수정일\n2025.01.23\t최초 등록일",
      "operation_period": "2025년 1월 1일 ~ 2025년 12월 31일",
      "application_period": "상시",
      "support_content": "○ 고용보험 미적용자 출산급여 - 총 150만원 - 유산, 사산의 경우는 임신 기간에 따라 급여 수준 상이 - 임신 기간 15주까지 : 30만원 / 16~21주 : 50만원 / 22~27주 : 100만원 / 28주 이상 : 150만원",
      "support_scale": null,
      "eligibility": {
        "income": {
          "description": "소득 활동 중"
        },
        "region": ["전국"]
      },
      "application_info": {
        "application_url": "https://www.gov.kr/portal/rcvfvrSvc/dtlEx/149200000153?administOrgCd=ALL",
        "managing_agency": "고용노동부",
        "operating_agency": "참고사이트 1"
      },
      "additional_info": {},
      "required_documents": [],
      "created_at": "2025-11-16T01:38:41.894493",
      "updated_at": "2025-11-16T01:38:41.894493"
    },
    {
      "id": 8,
      "policy_name": "고용유지지원금",
      "filename": "고용유지지원금_2025012200",
      "policy_number": "20250122005400110354",
      "region": "전국",
      "category": "일자리",
      "deadline": "상시",
      "summary": "경기변동, 산업구조의 변화 등에 따른 경영악화 로 고용조정이 불가피하게 된 사업주가 근로자를 퇴직시키지 않고 고용유지조치(휴업, 휴직, 무급휴업, 휴직 등)를 실시하는 경우 지원금을 지원함으로써 근로자의 실업 예방 및 생계안정 유지",
      "full_text": "전국\n일자리\n상시\n\n공유하기\n인쇄\n스크랩\n고용유지지원금\n최종 수정일2025년 1월 23일\n스크랩 수51\n조회수3920\n태그\n#보조금\n경기변동, 산업구조의 변화 등에 따른 경영악화 로 고용조정이 불가피하게 된 사업주가 근로자를 퇴직시키지 않고 고용유지조치(휴업, 휴직, 무급휴업, 휴직 등)를 실시하는 경우 지원금을 지원함으로써 근로자의 실업 예방 및 생계안정 유지\n\n한 눈에 보는 정책 요약\n한 눈에 보는 정책 요약 - 정책번호, 정책분야, 지원내용, 사업 운영 기간, 사업 신청기간, 지원 규모(명), 비고\n정책번호\n20250122005400110354\n정책분야\n일자리\n지원내용\n□ (지원한도 및 지원기간) 지원한도는 1일 상한액 6.6만원, 지원기간은 휴업.휴직을 합하여 연간 180일(무급휴업.휴직은 근로자별 재직기간 중 총 180일)\n\n□ (휴업) 1월간 총 근로시간의 20/100을 초과하여 휴업을 실시하고 휴업수당을 지급한 사업주에게 휴업수당의 2/3(대규모기업 1/2~2/3) 지원\n※ 특별고용지원업종, 고용위기지역은 휴업수당을 지급한 사업주에게 휴업수당의 9/10(대규모기업 2/3~3/4)\n\n□ (휴직) 근로자에게 1월 이상 휴직을 부여하고 휴직수당을 지급한 사업주에게 휴직수당의 2/3(대규모기업 1/2~2/3)를 지원\n\n□ (무급휴업ㆍ휴직) 근로자 평균임금의 50% 범위 내에서 직업안정기관의 장이 결정하여 지원\n사업 운영 기간\n95년~계속\n사업 신청기간\n상시\n지원 규모(명)\n제한없음\n신청자격\n신청자격 - 연령, 거주지역, 소득, 학력, 전공, 취업상태, 특화분야, 추가사항, 참여제한 대상\n연령\n제한없음\n거주지역\n전국\n소득\n무관\n학력\n제한없음\n전공\n제한없음\n취업상태\n제한없음\n특화분야\n제한없음\n추가사항\n□ 지원 요건\n○ 유급휴업: 1개월 단위 전체 피보험자 근로시간 대비 20% 초과 단축\n○ 유급휴직: 1개월 이상 근로 면제\n○ 무급휴업: 기준미달 휴업수당 지급에 대한 노동위원회 승인 필요, 30일 이상 실시, 기업규모별 최소 실시인원 충족\n- 19명 이하: 50% 이상, 99명 이하: 10명 이상, 100~999명: 10% 이상, 1,000명 이상: 100명 이상\n○ 무급휴직 : 실시전 1년 이내 유급휴업 또는 피보험자의 20% 이상 유급휴직 3개월 실시 필요, 30일 이상 실시, 기업규모별 최소 실시인원 충족\n- 99명 이하: 10명 이상, 100~999명: 10% 이상, 1,000명 이상: 100명 이상\n\n□ 지원제한 사유\n○ 계획신고된 고용유지조치기간과 이후 1개월간 정리해고, 사업주 권유 희망, 명예퇴직 등 피보험자의 인위적인 감원이 있을 경우\n○ 고용유지조치 기간 중 신규채용하는 경우\n○ 3년이상 연속하여 같은 달에 고용유지조치를 실시하는 경우(매출액 감소 원인이 계절적으로 당연한 경우)\n○ 과거 2년간 고용유지조치를 실시하고 지원금을 지원받은 경우, 해당 고용유지조치기간 종료일로부터 6개월내 피보험자의 10% 이상 고용조정시 신규지원 제한 ('24.7.1. 시행)\n○ 계획변경신청 없이 제출된 계획과 다르게 실시한 경우\n○ 고용보험료가 연체된 경우 등\n참여제한 대상\n□ 지원제외 대상 근로자(고용유지조치 대상자)\n○ 고용보험 피보험자격기간이 90일 이하인 자\n○ 일용근로자\n○ 근로기준법 제26조에 따라 해고가 예고된 자와 경영상 이유로 사업주 권고에 따라 퇴직이 예정된 자\n○ 사업주의 배우자 및 직계존·비속 관계인 자\n신청방법\n신청방법 - 신청절차, 심사 및 발표, 신청 사이트, 제출 서류\n신청절차\n□ 고용유지조치계획서 제출\n※ 유급은 실시 전날까지 제출, 무급은 실시 30일 전까지 제출\n\n□ 고용유지조치 실시\n※ 계획 변경시 변경예정일 전날까지(무급은 변경예정일 10일 전까지) 계획변경신고\n\n□ 실시종료 후 1개월 이내 지 지원금 신청\n심사 및 발표\n□ 지원요건 등 사실관계 확인 후 10일 이내 지급 결정\n※ 사실관계 확인 소요기간에 따라 통보 지연될 수 있음\n신청 사이트\nhttps://www.work24.go.kr\n제출 서류\n□ 계획신고시\n\n○ 고용유지조치계획서\n○ 매출액 장부, 매출처별 세금계산서 합계표, 손익계산서 또는 세금계산서 등 고용조정이 불가피함을 입증하는 서류\n○ 노사협의회 회의록, 대상자명단, 노사협의서 또는 근로자대표 선임서 등 사업주가 근로자 대표와 협의했음을 증명하는 서류\n○ 취업규칙 또는 단체협약 등 소정근로시간 기준 확인가능 서류\n○ 반복 정형화된 연장근로시간 확인 가능 서류(유급휴업)\n○ 파견 또는 도급관계 증명서류(파견ㆍ수급사업주)\n○ 휴업수당 적용제외 노동위원회 승인서(무급휴업)\n\n□ 지원금 신청시\n\n○ 지원금 신청서\n○ 근로자 월별 임금대장\n○ 출퇴근 현황 증명서류(유급휴업)\n○ 휴직수당지급대장 및 휴직 증명서류(유급휴직)\n기타\n기타 - 기타 정보, 주관 기관, 운영 기관, 참고사이트1, 참고사이트2\n기타 정보\n주관 기관\n고용노동부\n운영 기관\n참고사이트 1\nhttps://www.work24.go.kr\n참고사이트 2\nhttps://www.moel.go.kr\n정보 변경 내역\n정보 변경 내역 표로 변경일자, 변경 내용으로 구성되어있음\n변경일자\t변경 내용\n2025.01.23\t최종 수정일\n2025.01.22\t최초 등록일",
      "operation_period": "95년~계속",
      "application_period": "상시",
      "support_content": "※ 특별고용지원업종, 고용위기지역은 휴업수당을 지급한 사업주에게 휴업수당의 9/10(대규모기업 2/3~3/4)",
      "support_scale": null,
      "eligibility": {
        "income": {
          "description": "무관"
        },
        "region": ["전국"]
      },
      "application_info": {
        "application_url": "https://www.moel.go.kr",
        "managing_agency": "고용노동부",
        "operating_agency": "참고사이트 1"
      },
      "additional_info": {},
      "required_documents": [],
      "created_at": "2025-11-16T01:38:41.896314",
      "updated_at": "2025-11-16T01:38:41.896314"
    },
    {
      "id": 9,
      "policy_name": "구직급여",
      "filename": "구직급여_2025012200",
      "policy_number": "20250122005400110369",
      "region": "전국",
      "category": "일자리",
      "deadline": "상시",
      "summary": "고용보험 근로자가 실직하여 재취업 활동을 하는 기간에 소정의 급여를 지급함으로써 실업으로 인한 생계불안을 극복하고 생활의 안정을 도와주며 재취업의 기회를 지원해주는 제도",
      "full_text": "전국\n일자리\n상시\n\n공유하기\n인쇄\n스크랩\n구직급여\n최종 수정일2025년 1월 27일\n스크랩 수78\n조회수4175\n태그\n#맞춤형상담서비스\n고용보험 근로자가 실직하여 재취업 활동을 하는 기간에 소정의 급여를 지급함으로써 실업으로 인한 생계불안을 극복하고 생활의 안정을 도와주며 재취업의 기회를 지원해주는 제도\n\n한 눈에 보는 정책 요약\n한 눈에 보는 정책 요약 - 정책번호, 정책분야, 지원내용, 사업 운영 기간, 사업 신청기간, 지원 규모(명), 비고\n정책번호\n20250122005400110369\n정책분야\n일자리\n지원내용\n* 1일 구직급여 지급액\n1일 구직급여 지급액은 퇴직 전 3개월간의 1일 평균임금의 60퍼센트\n상한액은 1일 66,000원\n\n하한액은 1일 구직급여 수급액이 최저임금일액의 80퍼센트 미만인 경우에는 최저임금일액의 80퍼센트로 계산(1일 평균 소정근로시간이 8시간인 경우 2025.1.1. 이후 이직한 사람은 64,192원, 2024.1.1. 이후는 63,104원, 2023.1.1. 이후는 61,568원, 20191.1.~2020.12.31.에 이직한 사람은 60,120원)\n(이직일이 2019.10.1 이전은 1일 구직급여 수급액이 최저임금일액의 90퍼센트 미만인 경우에는 최저임금일액의 90퍼센트로 계산)\n\n최저 구직급여일액은 가입종료일을 기준으로 해당연도 최저임금일액으로 계산\n* 자영업자의 경우 구직급여, 직업능력개발수당, 광역구직활동비, 이주비는 적용되나, 연장급여, 조기재취업수당 등은 적용되지 않음\n\n* 예상지급일 수\n예상지급일 수는 퇴직 당시 연령 과 고용보험 가입기간에 따라 최소 120일에서 최대 270일까지로 계산 됩니다.\n\n구직급여에 관하여 궁금하신 내용은 실업급여 상세 안내 페이지\n사업 운영 기간\n연중\n사업 신청기간\n상시\n지원 규모(명)\n제한없음\n신청자격\n신청자격 - 연령, 거주지역, 소득, 학력, 전공, 취업상태, 특화분야, 추가사항, 참여제한 대상\n연령\n제한없음\n거주지역\n전국\n소득\n무관\n학력\n제한없음\n전공\n제한없음\n취업상태\n제한없음\n특화분야\n제한없음\n추가사항\n실업인정 차수별 재취업활동 횟수와 범위를 달리하고, 수급자별 특성에 맞게 차별하여 적용\n참여제한 대상\n신청방법\n신청방법 - 신청절차, 심사 및 발표, 신청 사이트, 제출 서류\n신청절차\n실업(고용보험 피보험자격 상실) > 고용24 구직등록 > 거주지 관할 고용센터 방문 > 수급자격인정신청 > 구직급여신청\n(지급요건 등 확인 work24.go.kr)\n심사 및 발표\n관할 고용센터 심사 후 발표\n신청 사이트\n제출 서류\n거주지 관할 고용센터 방문시 별도 안내\n기타\n기타 - 기타 정보, 주관 기관, 운영 기관, 참고사이트1, 참고사이트2\n기타 정보\n거주지별 고용센터 찾기\n주관 기관\n고용노동부\n운영 기관\n참고사이트 1\nhttps://work24.go.kr\n참고사이트 2\n정보 변경 내역\n정보 변경 내역 표로 변경일자, 변경 내용으로 구성되어있음\n변경일자\t변경 내용\n2025.01.27\t최종 수정일\n2025.01.22\t최초 등록일",
      "operation_period": "연중",
      "application_period": "상시",
      "support_content": "* 1일 구직급여 지급액 1일 구직급여 지급액은 퇴직 전 3개월간의 1일 평균임금의 60퍼센트 상한액은 1일 66,000원 하한액은 1일 구직급여 수급액이 최저임금일액의 80퍼센트 미만인 경우에는 최저임금일액의 80퍼센트로 계산(1일 평균 소정근로시간이 8시간인 경우 2025.1.1. 이후 이직한 사람은 64,192원, 2024.1.1. 이후는 63,104원, 2023.1.1. 이후는 61,568원, 20191.1.~2020.12.31.에 이직한 사람은 60,120원) (이직일이 2019.10.1 이전은 1일 구직급여 수급액이 최저임금일액의 90퍼센트 미만인 경우에는 최저임금일액의 90퍼센트로 계산) 최저 구직급여일액은 가입종료일을 기준으로 해당연도 최저임금일액으로 계산 * 자영업자의 경우 구직급여, 직업능력개발수당, 광역구직활동비, 이주비는 적용되나, 연장급여, 조기재취업수당 등은 적용되지 않음 * 예상지급일 수 예상지급일 수는 퇴직 당시 연령 과 고용보험 가입기간에 따라 최소 120일에서 최대 270일까지로 계산 됩니다. 구직급여에 관하여 궁금하신 내용은 실업급여 상세 안내 페이지",
      "support_scale": null,
      "eligibility": {
        "income": {
          "description": "무관"
        },
        "region": ["전국"]
      },
      "application_info": {
        "application_url": "https://work24.go.kr",
        "managing_agency": "고용노동부",
        "operating_agency": "참고사이트 1"
      },
      "additional_info": {},
      "required_documents": [
        {
          "id": 1,
          "name": "이직확인서",
          "notes": "퇴사 시 회사에서 발급",
          "description": null,
          "is_required": true,
          "issue_location": "이전 직장"
        },
        {
          "id": 2,
          "name": "신분증",
          "notes": null,
          "description": null,
          "is_required": true,
          "issue_location": "주민센터"
        },
        {
          "id": 3,
          "name": "통장사본",
          "notes": null,
          "description": null,
          "is_required": true,
          "issue_location": "은행"
        },
        {
          "id": 4,
          "name": "구직등록 확인서",
          "notes": "온라인 구직등록 후 발급",
          "description": null,
          "is_required": true,
          "issue_location": "워크넷"
        }
      ],
      "created_at": "2025-11-16T01:38:41.898077",
      "updated_at": "2025-11-16T01:38:41.898077"
    },
    {
      "id": 10,
      "policy_name": "기후동행카드(청년할인 서비스)",
      "filename": "기후동행카드청년할인_서비스_2025052200",
      "policy_number": "20250522005400210865",
      "region": "서울",
      "category": "복지문화",
      "deadline": "상시",
      "summary": "ㅇ 청년의 사회진출 지원 및 생활안정을 목적으로 청년할인 대상(만 19~39세)에게 기후동행카드 정기권의 할인 제공",
      "full_text": "서울\n복지문화\n상시\n\n공유하기\n인쇄\n스크랩\n기후동행카드(청년할인 서비스)\n최종 수정일2025년 6월 26일\n스크랩 수64\n조회수1716\n태그\n#보조금\nㅇ 청년의 사회진출 지원 및 생활안정을 목적으로 청년할인 대상(만 19~39세)에게 기후동행카드 정기권의 할인 제공\n\n한 눈에 보는 정책 요약\n한 눈에 보는 정책 요약 - 정책번호, 정책분야, 지원내용, 사업 운영 기간, 사업 신청기간, 지원 규모(명), 비고\n정책번호\n20250522005400210865\n정책분야\n복지문화\n지원내용\nㅇ 사업 근거\n- 「청년기본법」 제4조(국가와 지방자치단체의 책무) 1항\n- 「서울특별시 청년 기본 조례」 제15조(청년의 생활안정) 3항\n\nㅇ 추진 경과\n- 기후동행카드 기자설명회 : ’23.9.11\n- 기후동행카드 시범사업 서비스 개시 : ’24.1.27\n- 기후동행카드 청년할인 혜택 적용 : ’24.2.26\n- 본사업 개시(청년할인 적용 및 사후환급 추진) : ’24.7.1\n\nㅇ 사업 기간 : ’24.7.1. 이후~ 계속\n\nㅇ 사업 대상 : 만 19~39세에 해당하는 청년\n- ’24년 기준 ’85.1.1부터 ’05.12.31에 해당하는 모든 청년 대상\n- 단, 티머니 홈페이지 가입을 통해 본인 연령 인증 필수\n\nㅇ 사업 내용\n- 청년할인 연령 대상에게 기후동행카드 정기권 7천원 할인 혜택\n\nㅇ ’25년 사업비 : 10,500 백만원 (지방비 100%)\n사업 운영 기간\n2025년 1월 1일 ~ 2025년 12월 31일\n사업 신청기간\n상시\n지원 규모(명)\n0명\n신청자격\n신청자격 - 연령, 거주지역, 소득, 학력, 전공, 취업상태, 특화분야, 추가사항, 참여제한 대상\n연령\n만 19세~만 39세\n거주지역\n서울특별시 종로구, 서울특별시 중구, 서울특별시 용산구, 서울특별시 성동구, 서울특별시 광진구, 서울특별시 동대문구, 서울특별시 중랑구, 서울특별시 성북구, 서울특별시 강북구, 서울특별시 도봉구, 서울특별시 노원구, 서울특별시 은평구, 서울특별시 서대문구, 서울특별시 마포구, 서울특별시 양천구, 서울특별시 강서구, 서울특별시 구로구, 서울특별시 금천구, 서울특별시 영등포구, 서울특별시 동작구, 서울특별시 관악구, 서울특별시 서초구, 서울특별시 강남구, 서울특별시 송파구, 서울특별시 강동구\n소득\n무관\n학력\n제한없음\n전공\n제한없음\n취업상태\n제한없음\n특화분야\n제한없음\n추가사항\n참여제한 대상\n신청방법\n신청방법 - 신청절차, 심사 및 발표, 신청 사이트, 제출 서류\n신청절차\n심사 및 발표\n신청 사이트\n제출 서류\n기타\n기타 - 기타 정보, 주관 기관, 운영 기관, 참고사이트1, 참고사이트2\n기타 정보\n주관 기관\n교통기획관\n운영 기관\n참고사이트 1\n참고사이트 2\n정보 변경 내역\n정보 변경 내역 표로 변경일자, 변경 내용으로 구성되어있음\n변경일자\t변경 내용\n2025.06.26\t최종 수정일\n2025.05.22\t최초 등록일",
      "operation_period": "2025년 1월 1일 ~ 2025년 12월 31일",
      "application_period": "상시",
      "support_content": "ㅇ 사업 근거 - 「청년기본법」 제4조(국가와 지방자치단체의 책무) 1항 - 「서울특별시 청년 기본 조례」 제15조(청년의 생활안정) 3항 ㅇ 추진 경과 - 기후동행카드 기자설명회 : ’23.9.11 - 기후동행카드 시범사업 서비스 개시 : ’24.1.27 - 기후동행카드 청년할인 혜택 적용 : ’24.2.26 - 본사업 개시(청년할인 적용 및 사후환급 추진) : ’24.7.1 ㅇ 사업 기간 : ’24.7.1. 이후~ 계속 ㅇ 사업 대상 : 만 19~39세에 해당하는 청년 - ’24년 기준 ’85.1.1부터 ’05.12.31에 해당하는 모든 청년 대상 - 단, 티머니 홈페이지 가입을 통해 본인 연령 인증 필수 ㅇ 사업 내용 - 청년할인 연령 대상에게 기후동행카드 정기권 7천원 할인 혜택 ㅇ ’25년 사업비 : 10,500 백만원 (지방비 100%)",
      "support_scale": null,
      "eligibility": {
        "age": {
          "max": 39,
          "min": 19,
          "description": "만 19세~만 39세"
        },
        "income": {
          "description": "무관"
        },
        "region": [
          "서울특별시 종로구, 서울특별시 중구, 서울특별시 용산구, 서울특별시 성동구, 서울특별시 광진구, 서울특별시 동대문구, 서울특별시 중랑구, 서울특별시 성북구, 서울특별시 강북구, 서울특별시 도봉구, 서울특별시 노원구, 서울특별시 은평구, 서울특별시 서대문구, 서울특별시 마포구, 서울특별시 양천구, 서울특별시 강서구, 서울특별시 구로구, 서울특별시 금천구, 서울특별시 영등포구, 서울특별시 동작구, 서울특별시 관악구, 서울특별시 서초구, 서울특별시 강남구, 서울특별시 송파구, 서울특별시 강동구"
        ]
      },
      "application_info": {
        "managing_agency": "교통기획관",
        "operating_agency": "참고사이트 1"
      },
      "additional_info": {},
      "required_documents": [],
      "created_at": "2025-11-16T01:38:41.900546",
      "updated_at": "2025-11-16T01:38:41.900546"
    },
    {
      "id": 11,
      "policy_name": "미혼청년 주거급여 분리지급",
      "filename": "미혼청년_주거급여_분리지급_2025061700",
      "policy_number": "20250617005400110952",
      "region": "서울·부산·대구·인천·광주·대전·울산·세종·충청북도·충청남도·전라남도·경상북도·경상남도·제주·전북",
      "category": "주거",
      "deadline": "상시",
      "summary": "부모와 따로 거주하는 청년세대에게 주거급여를 별도 분리지급하여 안정적인 미래준비와 자립 도모",
      "full_text": "서울·부산·대구·인천·광주·대전·울산·세종·충청북도·충청남도·전라남도·경상북도·경상남도·제주·전북\n주거\n상시\n\n공유하기\n인쇄\n스크랩\n미혼청년 주거급여 분리지급\n최종 수정일2025년 6월 18일\n스크랩 수138\n조회수3803\n태그\n#주거지원\n부모와 따로 거주하는 청년세대에게 주거급여를 별도 분리지급하여 안정적인 미래준비와 자립 도모\n\n한 눈에 보는 정책 요약\n한 눈에 보는 정책 요약 - 정책번호, 정책분야, 지원내용, 사업 운영 기간, 사업 신청기간, 지원 규모(명), 비고\n정책번호\n20250617005400110952\n정책분야\n주거\n지원내용\n주거급여 수급가구원 중 취학,구직 등의 사유로 부모와 따로 거주하는 20대 미혼자녀에게 별도 주거급여 지급\n(지원내용) 부모와 청년 각각의 거주지, 가구원수에 따라 산정한 기준임대료를 상한으로 실제 임차료를 지급하고, 자기부담분은 분리된 가구 각각의 가구원 수에 비례하여 적용\n사업 운영 기간\n'21년~\n사업 신청기간\n상시\n지원 규모(명)\n0명\n신청자격\n신청자격 - 연령, 거주지역, 소득, 학력, 전공, 취업상태, 특화분야, 추가사항, 참여제한 대상\n연령\n만 19세~만 29세\n거주지역\n서울특별시 종로구, 서울특별시 중구, 서울특별시 용산구, 서울특별시 성동구, 서울특별시 광진구, 서울특별시 동대문구, 서울특별시 중랑구, 서울특별시 성북구, 서울특별시 강북구, 서울특별시 도봉구, 서울특별시 노원구, 서울특별시 은평구, 서울특별시 서대문구, 서울특별시 마포구, 서울특별시 양천구, 서울특별시 강서구, 서울특별시 구로구, 서울특별시 금천구, 서울특별시 영등포구, 서울특별시 동작구, 서울특별시 관악구, 서울특별시 서초구, 서울특별시 강남구, 서울특별시 송파구, 서울특별시 강동구, 부산광역시 중구, 부산광역시 서구, 부산광역시 동구, 부산광역시 영도구, 부산광역시 부산진구, 부산광역시 동래구, 부산광역시 남구, 부산광역시 북구, 부산광역시 해운대구, 부산광역시 사하구, 부산광역시 금정구, 부산광역시 강서구, 부산광역시 연제구, 부산광역시 수영구, 부산광역시 사상구, 부산광역시 기장군, 대구광역시 중구, 대구광역시 동구, 대구광역시 서구, 대구광역시 남구, 대구광역시 북구, 대구광역시 수성구, 대구광역시 달서구, 대구광역시 달성군, 대구광역시 군위군, 인천광역시 중구, 인천광역시 동구, 인천광역시 미추홀구, 인천광역시 연수구, 인천광역시 남동구, 인천광역시 부평구, 인천광역시 계양구, 인천광역시 서구, 인천광역시 강화군, 인천광역시 옹진군, 광주광역시 동구, 광주광역시 서구, 광주광역시 남구, 광주광역시 북구, 광주광역시 광산구, 대전광역시 동구, 대전광역시 중구, 대전광역시 서구, 대전광역시 유성구, 대전광역시 대덕구, 울산광역시 중구, 울산광역시 남구, 울산광역시 동구, 울산광역시 북구, 울산광역시 울주군, 세종특별자치시 세종특별자치시, 충청북도 청주시 상당구, 충청북도 청주시 서원구, 충청북도 청주시 흥덕구, 충청북도 청주시 청원구, 충청북도 충주시, 충청북도 제천시, 충청북도 보은군, 충청북도 옥천군, 충청북도 영동군, 충청북도 증평군, 충청북도 진천군, 충청북도 괴산군, 충청북도 음성군, 충청북도 단양군, 충청남도 천안시 동남구, 충청남도 천안시 서북구, 충청남도 공주시, 충청남도 보령시, 충청남도 아산시, 충청남도 서산시, 충청남도 논산시, 충청남도 계룡시, 충청남도 당진시, 충청남도 금산군, 충청남도 부여군, 충청남도 서천군, 충청남도 청양군, 충청남도 홍성군, 충청남도 예산군, 충청남도 태안군, 전라남도 목포시, 전라남도 여수시, 전라남도 순천시, 전라남도 나주시, 전라남도 광양시, 전라남도 담양군, 전라남도 곡성군, 전라남도 구례군, 전라남도 고흥군, 전라남도 보성군, 전라남도 화순군, 전라남도 장흥군, 전라남도 강진군, 전라남도 해남군, 전라남도 영암군, 전라남도 무안군, 전라남도 함평군, 전라남도 영광군, 전라남도 장성군, 전라남도 완도군, 전라남도 진도군, 전라남도 신안군, 경상북도 포항시 남구, 경상북도 포항시 북구, 경상북도 경주시, 경상북도 김천시, 경상북도 안동시, 경상북도 구미시, 경상북도 영주시, 경상북도 영천시, 경상북도 상주시, 경상북도 문경시, 경상북도 경산시, 경상북도 의성군, 경상북도 청송군, 경상북도 영양군, 경상북도 영덕군, 경상북도 청도군, 경상북도 고령군, 경상북도 성주군, 경상북도 칠곡군, 경상북도 예천군, 경상북도 봉화군, 경상북도 울진군, 경상북도 울릉군, 경상남도 창원시 의창구, 경상남도 창원시 성산구, 경상남도 창원시 마산합포구, 경상남도 창원시 마산회원구, 경상남도 창원시 진해구, 경상남도 진주시, 경상남도 통영시, 경상남도 사천시, 경상남도 김해시, 경상남도 밀양시, 경상남도 거제시, 경상남도 양산시, 경상남도 의령군, 경상남도 함안군, 경상남도 창녕군, 경상남도 고성군, 경상남도 남해군, 경상남도 하동군, 경상남도 산청군, 경상남도 함양군, 경상남도 거창군, 경상남도 합천군, 제주특별자치도 제주시, 제주특별자치도 서귀포시, 전북특별자치도 전주시 완산구, 전북특별자치도 전주시 덕진구, 전북특별자치도 군산시, 전북특별자치도 익산시, 전북특별자치도 정읍시, 전북특별자치도 남원시, 전북특별자치도 김제시, 전북특별자치도 완주군, 전북특별자치도 진안군, 전북특별자치도 무주군, 전북특별자치도 장수군, 전북특별자치도 임실군, 전북특별자치도 순창군, 전북특별자치도 고창군, 전북특별자치도 부안군\n소득\n중위소득 48% 이하\n학력\n제한없음\n전공\n제한없음\n취업상태\n제한없음\n특화분야\n제한없음\n추가사항\n주거급여 수급가구 내 부모와 떨어져 사는 청년에게 주거급여를 분리하여 지급\n- 임차급여 또는 수선유지급여를 지급받는 수급가구 내 만 19세 이상 30세 미만의 미혼자녀\n- 청년명의의 임대차계약을 체결하고 임차료를 지불하는 청년에게 지급(전입신고 필수)\n- 주거급여 수급가구의 부모와 청년이 주민등록상 시·군을 달리하는 경우 인정하되, 동일 시·군이라도 보장기관이 인정하는 경우는 예외로 함\n참여제한 대상\n주거급여가 불필요하거나, 타 법령 등에 의하여 주거를 제공받고 있는 수급자에 대해서는 주거급여를 지급하지 않음\n신청방법\n신청방법 - 신청절차, 심사 및 발표, 신청 사이트, 제출 서류\n신청절차\n□ 읍면동 주민센터에 관련 상담 신청 → 신청서, 금융정보 등 제공 동의서, 임대차 계약서(해당자 한함) 등 기타 구비서류 안내받아 접수\n□ 복지로 서비스신청을 통한 온라인신청 : 복지로 로그인 > 서비스 신청 > 복지서비스 신청 > 복지급여 신청 > 저소득층 > '주거급여' 또는 '청년주거급여분리지급'\n심사 및 발표\n신청 사이트\nhttps://www.bokjiro.go.kr/ssis-tbu/twataa/wlfareInfo/moveTWAT52011M.do?wlfareInfoId=WLF00003201\n제출 서류\n기타\n기타 - 기타 정보, 주관 기관, 운영 기관, 참고사이트1, 참고사이트2\n기타 정보\n주관 기관\n국토교통부\n운영 기관\n참고사이트 1\n참고사이트 2",
      "operation_period": "'21년~",
      "application_period": "상시",
      "support_content": "주거급여 수급가구원 중 취학,구직 등의 사유로 부모와 따로 거주하는 20대 미혼자녀에게 별도 주거급여 지급 (지원내용) 부모와 청년 각각의 거주지, 가구원수에 따라 산정한 기준임대료를 상한으로 실제 임차료를 지급하고, 자기부담분은 분리된 가구 각각의 가구원 수에 비례하여 적용",
      "support_scale": null,
      "eligibility": {
        "age": {
          "max": 29,
          "min": 19,
          "description": "만 19세~만 29세"
        },
        "income": {
          "description": "중위소득 48% 이하"
        },
        "region": [
          "서울특별시 종로구, 서울특별시 중구, 서울특별시 용산구, 서울특별시 성동구, 서울특별시 광진구, 서울특별시 동대문구, 서울특별시 중랑구, 서울특별시 성북구, 서울특별시 강북구, 서울특별시 도봉구, 서울특별시 노원구, 서울특별시 은평구, 서울특별시 서대문구, 서울특별시 마포구, 서울특별시 양천구, 서울특별시 강서구, 서울특별시 구로구, 서울특별시 금천구, 서울특별시 영등포구, 서울특별시 동작구, 서울특별시 관악구, 서울특별시 서초구, 서울특별시 강남구, 서울특별시 송파구, 서울특별시 강동구, 부산광역시 중구, 부산광역시 서구, 부산광역시 동구, 부산광역시 영도구, 부산광역시 부산진구, 부산광역시 동래구, 부산광역시 남구, 부산광역시 북구, 부산광역시 해운대구, 부산광역시 사하구, 부산광역시 금정구, 부산광역시 강서구, 부산광역시 연제구, 부산광역시 수영구, 부산광역시 사상구, 부산광역시 기장군, 대구광역시 중구, 대구광역시 동구, 대구광역시 서구, 대구광역시 남구, 대구광역시 북구, 대구광역시 수성구, 대구광역시 달서구, 대구광역시 달성군, 대구광역시 군위군, 인천광역시 중구, 인천광역시 동구, 인천광역시 미추홀구, 인천광역시 연수구, 인천광역시 남동구, 인천광역시 부평구, 인천광역시 계양구, 인천광역시 서구, 인천광역시 강화군, 인천광역시 옹진군, 광주광역시 동구, 광주광역시 서구, 광주광역시 남구, 광주광역시 북구, 광주광역시 광산구, 대전광역시 동구, 대전광역시 중구, 대전광역시 서구, 대전광역시 유성구, 대전광역시 대덕구, 울산광역시 중구, 울산광역시 남구, 울산광역시 동구, 울산광역시 북구, 울산광역시 울주군, 세종특별자치시 세종특별자치시, 충청북도 청주시 상당구, 충청북도 청주시 서원구, 충청북도 청주시 흥덕구, 충청북도 청주시 청원구, 충청북도 충주시, 충청북도 제천시, 충청북도 보은군, 충청북도 옥천군, 충청북도 영동군, 충청북도 증평군, 충청북도 진천군, 충청북도 괴산군, 충청북도 음성군, 충청북도 단양군, 충청남도 천안시 동남구, 충청남도 천안시 서북구, 충청남도 공주시, 충청남도 보령시, 충청남도 아산시, 충청남도 서산시, 충청남도 논산시, 충청남도 계룡시, 충청남도 당진시, 충청남도 금산군, 충청남도 부여군, 충청남도 서천군, 충청남도 청양군, 충청남도 홍성군, 충청남도 예산군, 충청남도 태안군, 전라남도 목포시, 전라남도 여수시, 전라남도 순천시, 전라남도 나주시, 전라남도 광양시, 전라남도 담양군, 전라남도 곡성군, 전라남도 구례군, 전라남도 고흥군, 전라남도 보성군, 전라남도 화순군, 전라남도 장흥군, 전라남도 강진군, 전라남도 해남군, 전라남도 영암군, 전라남도 무안군, 전라남도 함평군, 전라남도 영광군, 전라남도 장성군, 전라남도 완도군, 전라남도 진도군, 전라남도 신안군, 경상북도 포항시 남구, 경상북도 포항시 북구, 경상북도 경주시, 경상북도 김천시, 경상북도 안동시, 경상북도 구미시, 경상북도 영주시, 경상북도 영천시, 경상북도 상주시, 경상북도 문경시, 경상북도 경산시, 경상북도 의성군, 경상북도 청송군, 경상북도 영양군, 경상북도 영덕군, 경상북도 청도군, 경상북도 고령군, 경상북도 성주군, 경상북도 칠곡군, 경상북도 예천군, 경상북도 봉화군, 경상북도 울진군, 경상북도 울릉군, 경상남도 창원시 의창구, 경상남도 창원시 성산구, 경상남도 창원시 마산합포구, 경상남도 창원시 마산회원구, 경상남도 창원시 진해구, 경상남도 진주시, 경상남도 통영시, 경상남도 사천시, 경상남도 김해시, 경상남도 밀양시, 경상남도 거제시, 경상남도 양산시, 경상남도 의령군, 경상남도 함안군, 경상남도 창녕군, 경상남도 고성군, 경상남도 남해군, 경상남도 하동군, 경상남도 산청군, 경상남도 함양군, 경상남도 거창군, 경상남도 합천군, 제주특별자치도 제주시, 제주특별자치도 서귀포시, 전북특별자치도 전주시 완산구, 전북특별자치도 전주시 덕진구, 전북특별자치도 군산시, 전북특별자치도 익산시, 전북특별자치도 정읍시, 전북특별자치도 남원시, 전북특별자치도 김제시, 전북특별자치도 완주군, 전북특별자치도 진안군, 전북특별자치도 무주군, 전북특별자치도 장수군, 전북특별자치도 임실군, 전북특별자치도 순창군, 전북특별자치도 고창군, 전북특별자치도 부안군"
        ]
      },
      "application_info": {
        "managing_agency": "국토교통부",
        "operating_agency": "참고사이트 1"
      },
      "additional_info": {},
      "required_documents": [],
      "created_at": "2025-11-16T01:38:41.902328",
      "updated_at": "2025-11-16T01:38:41.902328"
    },
    {
      "id": 12,
      "policy_name": "빈곤 청년에 대한 근로인센티브 확대",
      "filename": "빈곤_청년에_대한_근로인센티브_확대_2025061700",
      "policy_number": "20250617005400110946",
      "region": "전국",
      "category": "복지문화",
      "deadline": "상시",
      "summary": "빈곤 청년에 대한 근로인센티브 확대",
      "full_text": "전국\n복지문화\n상시\n\n공유하기\n인쇄\n스크랩\n빈곤 청년에 대한 근로인센티브 확대\n최종 수정일2025년 6월 26일\n스크랩 수68\n조회수981\n태그\n#보조금\n빈곤 청년에 대한 근로인센티브 확대\n\n한 눈에 보는 정책 요약\n한 눈에 보는 정책 요약 - 정책번호, 정책분야, 지원내용, 사업 운영 기간, 사업 신청기간, 지원 규모(명), 비고\n정책번호\n20250617005400110946\n정책분야\n복지문화\n지원내용\n○ 근로·사업소득 공제\n- (30세 미만 청년 또는 대학생) 40만원+30% 공제\n- (자립준비청년, 청소년 복지시설 퇴소 청소년, 청소년 한부모) 60만원+30% 공제\n\n○ 등록금 공제\n- 대학생의 등록금을 대학생 본인 또는 가구의 근로·사업소득으로 지출한 경우 해당 지출금액을 소득 산정 시 공제\n\n○ 자립지원 별도가구 보장\n- 청년층(18~34세)이 포함된 가구가 청년층 소득으로 인해 선정기준을 초과할 경우 해당 청년을 가구에서 제외하여 나머지 가구원의 수급권 보호\n\n○ 소득·재산 공제\n- 소득인정액 산정 시 자시돌봄청년에게 지급되는 자기돌봄비, 자립준비청년 등 복지시설 퇴소 청년에게 지급되는 자립수당 및 자립 정착금을 수급자의 소득·재산에서 공제\n사업 운영 기간\n2025년 1월 1일 ~ 2025년 12월 31일\n사업 신청기간\n상시\n지원 규모(명)\n제한없음\n신청자격\n신청자격 - 연령, 거주지역, 소득, 학력, 전공, 취업상태, 특화분야, 추가사항, 참여제한 대상\n연령\n만 18세~만 34세\n거주지역\n전국\n소득\n가구의 소득인정액이 생계급여 선정기준 이하\n학력\n제한없음\n전공\n제한없음\n취업상태\n제한없음\n특화분야\n제한없음\n추가사항\n생계와 주거를 달리하는 1촌 혈족 및 그 배우자의 소득·재산이 일정 기준(연소득 1.3억원, 일반재산 12억원) 이하\n참여제한 대상\n특례 미적용 외국인\n신청방법\n신청방법 - 신청절차, 심사 및 발표, 신청 사이트, 제출 서류\n신청절차\n읍면동 행정복지센터 또는 시군구청 방문\n심사 및 발표\n신청 사이트\n제출 서류\nㅇ사회보장급여 신청(변경)서\nㅇ금융정보 등 제공 동의서\nㅇ기타 구비서류\n기타\n기타 - 기타 정보, 주관 기관, 운영 기관, 참고사이트1, 참고사이트2\n기타 정보\n주관 기관\n복지정책관\n운영 기관\n참고사이트 1\n참고사이트 2\n정보 변경 내역\n정보 변경 내역 표로 변경일자, 변경 내용으로 구성되어있음\n변경일자\t변경 내용\n2025.06.26\t최종 수정일\n2025.06.17\t최초 등록일",
      "operation_period": "2025년 1월 1일 ~ 2025년 12월 31일",
      "application_period": "상시",
      "support_content": "○ 근로·사업소득 공제 - (30세 미만 청년 또는 대학생) 40만원+30% 공제 - (자립준비청년, 청소년 복지시설 퇴소 청소년, 청소년 한부모) 60만원+30% 공제 ○ 등록금 공제 - 대학생의 등록금을 대학생 본인 또는 가구의 근로·사업소득으로 지출한 경우 해당 지출금액을 소득 산정 시 공제 ○ 자립지원 별도가구 보장 - 청년층(18~34세)이 포함된 가구가 청년층 소득으로 인해 선정기준을 초과할 경우 해당 청년을 가구에서 제외하여 나머지 가구원의 수급권 보호 ○ 소득·재산 공제 - 소득인정액 산정 시 자시돌봄청년에게 지급되는 자기돌봄비, 자립준비청년 등 복지시설 퇴소 청년에게 지급되는 자립수당 및 자립 정착금을 수급자의 소득·재산에서 공제",
      "support_scale": null,
      "eligibility": {
        "age": {
          "max": 34,
          "min": 18,
          "description": "만 18세~만 34세"
        },
        "income": {
          "description": "가구의 소득인정액이 생계급여 선정기준 이하"
        },
        "region": ["전국"]
      },
      "application_info": {
        "managing_agency": "복지정책관",
        "operating_agency": "참고사이트 1"
      },
      "additional_info": {},
      "required_documents": [],
      "created_at": "2025-11-16T01:38:41.905818",
      "updated_at": "2025-11-16T01:38:41.905818"
    },
    {
      "id": 13,
      "policy_name": "서울시 고립·은둔청년 지원사업",
      "filename": "서울시_고립_은둔청년_지원사업_2025051900",
      "policy_number": "20250519005400210859",
      "region": "서울",
      "category": "복지문화",
      "deadline": "상시",
      "summary": "ㅇ 청년정책 사각지대에 놓인 고립·은둔청년에 대한 발굴과 맞춤 지원을 통해 청년의 사회성, 대인관계 능력 향상지원 및 사회진입 촉진",
      "full_text": "서울\n복지문화\n상시\n\n공유하기\n인쇄\n스크랩\n서울시 고립·은둔청년 지원사업\n최종 수정일2025년 6월 26일\n스크랩 수13\n조회수1302\n태그\n#맞춤형상담서비스\nㅇ 청년정책 사각지대에 놓인 고립·은둔청년에 대한 발굴과 맞춤 지원을 통해 청년의 사회성, 대인관계 능력 향상지원 및 사회진입 촉진\n\n한 눈에 보는 정책 요약\n한 눈에 보는 정책 요약 - 정책번호, 정책분야, 지원내용, 사업 운영 기간, 사업 신청기간, 지원 규모(명), 비고\n정책번호\n20250519005400210859\n정책분야\n복지문화\n지원내용\nㅇ (사업 근거)\n- 청년기본법 제21조(청년 복지증진)\n- 서울특별시 청년기본조례 제12조(청년의 고용확대 등), 제15조(청년의 생활안정), 제18조(청년의 건강증진)\n- 서울특별시 사회적 고립청년 지원에 관한 조례\n\nㅇ (추진 경과)\n- 2019년 : 고립청년 밀착지원 사업(시범사업) 추진\n- 2020년~ : 서울시 고립청년 사회적 자립 지원사업\n- 2021년 : 서울시 사회적 고립청년 지원에 관한 조례 제정\n- 2022년 : 서울시 고립·은둔청년 실태조사 실시\n- 2023년 : 서울시 고립·은둔청년 종합지원 계획 수립\n- 2024년 : 고립‧은둔청년 전담기관 ’서울청년기지개센터‘ 개관\n\nㅇ (사업 기간) ‘20년~\n\nㅇ (사업 대상) 서울시 거주 19~39세 고립·은둔 청년\n- (연령 기준) 19~39세\n- (소득 기준) 없음\n\nㅇ (사업 내용) 고립·은둔청년과 가족에 대한 종합적·체계적 맞춤지원\n- (원스톱 지원) 발굴→진단→지원→사회진입→사후관리까지 통합 지원·관리\n- (주변인 지원) 부모 등 주변인 대상 실전형 교육, 상담 및 자조모임 지원\n- (생태계 조성) 민·관 다양한 자원 발굴, 연계로 자기주도 회복 지원\n\nㅇ (사업비) 4,329백만원 (지방비 4,329백만원)\n사업 운영 기간\n2025년 1월 1일 ~ 2025년 12월 31일\n사업 신청기간\n상시\n지원 규모(명)\n0명\n신청자격\n신청자격 - 연령, 거주지역, 소득, 학력, 전공, 취업상태, 특화분야, 추가사항, 참여제한 대상\n연령\n만 19세~만 39세\n거주지역\n서울특별시 종로구, 서울특별시 중구, 서울특별시 용산구, 서울특별시 성동구, 서울특별시 광진구, 서울특별시 동대문구, 서울특별시 중랑구, 서울특별시 성북구, 서울특별시 강북구, 서울특별시 도봉구, 서울특별시 노원구, 서울특별시 은평구, 서울특별시 서대문구, 서울특별시 마포구, 서울특별시 양천구, 서울특별시 강서구, 서울특별시 구로구, 서울특별시 금천구, 서울특별시 영등포구, 서울특별시 동작구, 서울특별시 관악구, 서울특별시 서초구, 서울특별시 강남구, 서울특별시 송파구, 서울특별시 강동구\n소득\n무관\n학력\n제한없음\n전공\n제한없음\n취업상태\n제한없음\n특화분야\n제한없음\n추가사항\n참여제한 대상\n신청방법\n신청방법 - 신청절차, 심사 및 발표, 신청 사이트, 제출 서류\n신청절차\n심사 및 발표\n신청 사이트\n제출 서류\n기타\n기타 - 기타 정보, 주관 기관, 운영 기관, 참고사이트1, 참고사이트2\n기타 정보\n주관 기관\n청년사업담당관\n운영 기관\n참고사이트 1\n참고사이트 2\n정보 변경 내역\n정보 변경 내역 표로 변경일자, 변경 내용으로 구성되어있음\n변경일자\t변경 내용\n2025.06.26\t최종 수정일\n2025.05.19\t최초 등록일",
      "operation_period": "2025년 1월 1일 ~ 2025년 12월 31일",
      "application_period": "상시",
      "support_content": "ㅇ (사업 근거) - 청년기본법 제21조(청년 복지증진) - 서울특별시 청년기본조례 제12조(청년의 고용확대 등), 제15조(청년의 생활안정), 제18조(청년의 건강증진) - 서울특별시 사회적 고립청년 지원에 관한 조례 ㅇ (추진 경과) - 2019년 : 고립청년 밀착지원 사업(시범사업) 추진 - 2020년~ : 서울시 고립청년 사회적 자립 지원사업 - 2021년 : 서울시 사회적 고립청년 지원에 관한 조례 제정 - 2022년 : 서울시 고립·은둔청년 실태조사 실시 - 2023년 : 서울시 고립·은둔청년 종합지원 계획 수립 - 2024년 : 고립‧은둔청년 전담기관 ’서울청년기지개센터‘ 개관 ㅇ (사업 기간) ‘20년~ ㅇ (사업 대상) 서울시 거주 19~39세 고립·은둔 청년 - (연령 기준) 19~39세 - (소득 기준) 없음 ㅇ (사업 내용) 고립·은둔청년과 가족에 대한 종합적·체계적 맞춤지원 - (원스톱 지원) 발굴→진단→지원→사회진입→사후관리까지 통합 지원·관리 - (주변인 지원) 부모 등 주변인 대상 실전형 교육, 상담 및 자조모임 지원 - (생태계 조성) 민·관 다양한 자원 발굴, 연계로 자기주도 회복 지원 ㅇ (사업비) 4,329백만원 (지방비 4,329백만원)",
      "support_scale": null,
      "eligibility": {
        "age": {
          "max": 39,
          "min": 19,
          "description": "만 19세~만 39세"
        },
        "income": {
          "description": "무관"
        },
        "region": [
          "서울특별시 종로구, 서울특별시 중구, 서울특별시 용산구, 서울특별시 성동구, 서울특별시 광진구, 서울특별시 동대문구, 서울특별시 중랑구, 서울특별시 성북구, 서울특별시 강북구, 서울특별시 도봉구, 서울특별시 노원구, 서울특별시 은평구, 서울특별시 서대문구, 서울특별시 마포구, 서울특별시 양천구, 서울특별시 강서구, 서울특별시 구로구, 서울특별시 금천구, 서울특별시 영등포구, 서울특별시 동작구, 서울특별시 관악구, 서울특별시 서초구, 서울특별시 강남구, 서울특별시 송파구, 서울특별시 강동구"
        ]
      },
      "application_info": {
        "managing_agency": "청년사업담당관",
        "operating_agency": "참고사이트 1"
      },
      "additional_info": {},
      "required_documents": [],
      "created_at": "2025-11-16T01:38:41.909953",
      "updated_at": "2025-11-16T01:38:41.909953"
    },
    {
      "id": 14,
      "policy_name": "예술인 고용보험",
      "filename": "예술인_고용보험_2025012300",
      "policy_number": "20250123005400110401",
      "region": "전국",
      "category": "일자리",
      "deadline": "상시",
      "summary": "문화예술용역 계약을 체결한 예술인에 대한 고용보험 적용을 통해 실업급여·출산전후급여 지급을 통한 고용안전망 확충",
      "full_text": "전국\n일자리\n상시\n\n공유하기\n인쇄\n스크랩\n예술인 고용보험\n최종 수정일2025년 2월 7일\n스크랩 수21\n조회수1487\n태그\n#보조금\n문화예술용역 계약을 체결한 예술인에 대한 고용보험 적용을 통해 실업급여·출산전후급여 지급을 통한 고용안전망 확충\n\n한 눈에 보는 정책 요약\n한 눈에 보는 정책 요약 - 정책번호, 정책분야, 지원내용, 사업 운영 기간, 사업 신청기간, 지원 규모(명), 비고\n정책번호\n20250123005400110401\n정책분야\n일자리\n지원내용\n□ 실업 시 생활안정과 구직활동 촉진을 위한 실업급여 지급\n○ 지급수준: 구직급여일액은 기초일액의 60퍼센트, 상한액은 근로자와 동일(66,000원)\n* 기초일액: 마지막 이직일 전 1년 간 신고된 보수총액을 해당 기간의 총일수로 나눈 금액\n○ 지급기간: 피보험기간 및 연령에 따라 120 ~ 270일 지급\n□ 재직 중 출산전후급여 지급\n○ 지급수준: 1년간 월평균 보수의 100퍼센트(상한액 월 210만원, 하한액 60만원)\n○ 지급기간: 출산전후를 더하여 90일(한 번에 둘 이상 자녀를 임신한 경우 120일)\n사업 운영 기간\n연중\n사업 신청기간\n상시\n지원 규모(명)\n0명\n신청자격\n신청자격 - 연령, 거주지역, 소득, 학력, 전공, 취업상태, 특화분야, 추가사항, 참여제한 대상\n연령\n제한없음\n거주지역\n전국\n소득\n월평균소득 50만원 이상 / ① 단기예술인(1개월 미만 계약자)은 소득요건 없음 ② 소득요건 미충족 일반예술인도 다른 문화예술용역 계약과의 소득합산 시 50만원 이상인 경우 적용\n학력\n제한없음\n전공\n제한없음\n취업상태\n제한없음\n특화분야\n제한없음\n추가사항\n1. 실업급여\n- 수급요건: 이직일 이전 24개월 동안 피보험 단위기간이 9개월 이상\n- 지급수준: 구직급여일액은 기초일액의 60퍼센트, 상한액은 근로자와 동일(66,000원)\n기초일액: 마지막 이직일 전 1년 간 신고된 보수총액을 해당 기간의 총일수로 나눈 금액\n- 지급기간: 피보험기간 및 연령에 따라 120 ~ 270일 지급\n\n2. 출산전후급여\n- 수급요건: 출산(유산 및 사산)일 전 피보험단위기간이 3개월 이상일 것\n- 지급수준: 1년간 월평균 보수의 100퍼센트(상한액 월 210만원, 하한액 60만원)\n- 지급기간: 출산전후를 더하여 90일(한 번에 둘 이상 자녀를 임신한 경우 120일)\n참여제한 대상\n1. 문화예술용역 계약의 월평균소득 50만원 미만인 경우(단기예술인 (1개월 미만 계약자)은 일정소득 미충족시에도 고용보험 적용). 단, 계약건별 합산한 월평균소득이 50만원이상인 경우, 예술인의 직접신청에 의하여 당연적용\n2. 65세 이상 신규계약자(실업급여·출산전후급여 미지급)\n신청방법\n신청방법 - 신청절차, 심사 및 발표, 신청 사이트, 제출 서류\n신청절차\n□ 고용보험 가입 신청은 원칙적으로 사업주가 신고\n(단, 개별 계약의 월평균소득이 50만원 미만이어도여러 계약을 합하여 월평균소득이 50만원 이상인 경우, 예술인이 직접 고용보험 가입 신청)\n□ 신고방법\n○ 온라인 신고: 고용ㆍ산재보험토탈서비스(https://total.comwel.or.kr)로 접속, 민원접수/신고>노무제공자ㆍ예술인>취득ㆍ상실 및 노무제공내용확인신고 등\n○ 방문 신고: 서울특수형태근로종사자센터 예술인가입부 및 공단 각 지사에 예술인 고용보험 피보험자격 취득ㆍ상실 및 노무제공내용확인신고서 등 제출\n심사 및 발표\n신청 사이트\nhttps://total.comwel.or.kr\n제출 서류\n(자격취득 등 신고)피보험자격 취득ㆍ상실신고서, 노무제공내용확인신고서\n(급여신청)거주지 관할 고용센터 방문시 별도 안내\n기타\n기타 - 기타 정보, 주관 기관, 운영 기관, 참고사이트1, 참고사이트2\n기타 정보\n① 가입 요건은 고용 대신 문화예술용역 관련 계약임. 사업주와 예술인이 체결한 문화예술용역 관련 계약의 기간과 소득으로 고용보험 가입\n② 계약 금액이 월평균 50만원 이상이면 당연가입.\n소득이 월급여 형태가 아니어도, 예술인의 대가(보수) 지급 시 사업주가 0.8% 원천징수하여 사업주의 보험료(0.8%)와 함께 매월 납부\n③ 50만원 미만의 소득도 다른 계약 건과 합산하여 월평균소득 50만원이면 가입 가능. 이 경우 예술인이 직접 피보험자격 소득합산신청서 제출하여 고용보험 가입\n④ 피보험자격 이중취득 가능. 근로자고용보험 + 예술인고용보험, 예술인고용보험 + 예술인고용보험 이중가입 가능\n⑤ 실업급여 수급 중 일부 소득활동을 인정. 예술인은 실업인정대상 기간 중 소득이 발생한 경우에는 구직급여일액을 전부 감액하거나, 일부 감액하고 지급함\n주관 기관\n고용노동부\n운영 기관\n참고사이트 1\nhttps://work24.go.kr\n참고사이트 2\nhttp://kawf.kr/aei/artMain.do\n정보 변경 내역\n정보 변경 내역 표로 변경일자, 변경 내용으로 구성되어있음\n변경일자\t변경 내용\n2025.02.07\t최종 수정일\n2025.01.23\t최초 등록일",
      "operation_period": "연중",
      "application_period": "상시",
      "support_content": "○ 지급수준: 구직급여일액은 기초일액의 60퍼센트, 상한액은 근로자와 동일(66,000원) * 기초일액: 마지막 이직일 전 1년 간 신고된 보수총액을 해당 기간의 총일수로 나눈 금액 ○ 지급기간: 피보험기간 및 연령에 따라 120 ~ 270일 지급 ○ 지급수준: 1년간 월평균 보수의 100퍼센트(상한액 월 210만원, 하한액 60만원) ○ 지급기간: 출산전후를 더하여 90일(한 번에 둘 이상 자녀를 임신한 경우 120일)",
      "support_scale": null,
      "eligibility": {
        "income": {
          "description": "월평균소득 50만원 이상 / ① 단기예술인(1개월 미만 계약자)은 소득요건 없음 ② 소득요건 미충족 일반예술인도 다른 문화예술용역 계약과의 소득합산 시 50만원 이상인 경우 적용"
        },
        "region": ["전국"]
      },
      "application_info": {
        "application_url": "http://kawf.kr/aei/artMain.do",
        "managing_agency": "고용노동부",
        "operating_agency": "참고사이트 1"
      },
      "additional_info": {},
      "required_documents": [],
      "created_at": "2025-11-16T01:38:41.916926",
      "updated_at": "2025-11-16T01:38:41.916926"
    },
    {
      "id": 15,
      "policy_name": "자립준비청년 의료비 지원 사업",
      "filename": "자립준비청년_의료비_지원_사업_2025061700",
      "policy_number": "20250617005400110945",
      "region": "전국",
      "category": "복지문화",
      "deadline": "상시",
      "summary": "건강보험 가입 자립준비청년을 대상으로 차상위 본인부담경감 대상자와 유사한 수준에서 의료 이용이 가능하도록 요양급여비용 본인일부부담금 차액을 지원",
      "full_text": "전국\n복지문화\n상시\n\n공유하기\n인쇄\n스크랩\n자립준비청년 의료비 지원 사업\n최종 수정일2025년 6월 26일\n스크랩 수30\n조회수689\n태그\n#보조금\n건강보험 가입 자립준비청년을 대상으로 차상위 본인부담경감 대상자와 유사한 수준에서 의료 이용이 가능하도록 요양급여비용 본인일부부담금 차액을 지원\n\n한 눈에 보는 정책 요약\n한 눈에 보는 정책 요약 - 정책번호, 정책분야, 지원내용, 사업 운영 기간, 사업 신청기간, 지원 규모(명), 비고\n정책번호\n20250617005400110945\n정책분야\n복지문화\n지원내용\n건강보험 가입 자립준비청년을 대상으로 차상위 본인부담경감 대상자와 유사한 수준에서 의료 이용이 가능하도록 요양급여비용 본인일부부담금 차액을 지원\n사업 운영 기간\n상시\n사업 신청기간\n상시\n지원 규모(명)\n제한없음\n신청자격\n신청자격 - 연령, 거주지역, 소득, 학력, 전공, 취업상태, 특화분야, 추가사항, 참여제한 대상\n연령\n만 18세~만 29세\n거주지역\n전국\n소득\n무관\n학력\n제한없음\n전공\n제한없음\n취업상태\n제한없음\n특화분야\n기타\n추가사항\n1. 아동복지시설, 가정위탁 보호종료 아동 중 보호종료일 기준으로 과거 2년 이상 연속하여 보호를 받은 자로서 다음 사항 중 어느 하나에 해당하는 경우\n- 만 18세 이후 만기 및 연장 보호종료 또는 재보호종료된 자로서 보호종료 5년 이내인 자(단, '18.8월 이후 보호종료된 자)\n- 만 15세 이후 보호조치가 조기 종료된 자로서 만 18세가 된 때로부터 5년 이내인 자(단, 아동복지법 시행('24.2.9.)이후 만 18세가 된 자부터 적용)\n2. 건강보험 가입자 또는 피부양자\n- 차상위본인부담 경감대상자는 제외\n1,2 조건을 모두 충족하는 자\n참여제한 대상\n신청방법\n신청방법 - 신청절차, 심사 및 발표, 신청 사이트, 제출 서류\n신청절차\n읍면동 행정복지센터에 자립준비청년 의료비 지원 신청\n심사 및 발표\n신청 사이트\n제출 서류\n자립준비청년 의료비 지원 신청서 1부, 신분증, 보호종료확인서 등\n기타\n기타 - 기타 정보, 주관 기관, 운영 기관, 참고사이트1, 참고사이트2\n기타 정보\n주관 기관\n인구아동정책관\n운영 기관\n참고사이트 1\n참고사이트 2\n정보 변경 내역\n정보 변경 내역 표로 변경일자, 변경 내용으로 구성되어있음\n변경일자\t변경 내용\n2025.06.26\t최종 수정일\n2025.06.17\t최초 등록일",
      "operation_period": "상시",
      "application_period": "상시",
      "support_content": "건강보험 가입 자립준비청년을 대상으로 차상위 본인부담경감 대상자와 유사한 수준에서 의료 이용이 가능하도록 요양급여비용 본인일부부담금 차액을 지원",
      "support_scale": null,
      "eligibility": {
        "age": {
          "max": 29,
          "min": 18,
          "description": "만 18세~만 29세"
        },
        "income": {
          "description": "무관"
        },
        "region": ["전국"]
      },
      "application_info": {
        "managing_agency": "인구아동정책관",
        "operating_agency": "참고사이트 1"
      },
      "additional_info": {},
      "required_documents": [],
      "created_at": "2025-11-16T01:38:41.918678",
      "updated_at": "2025-11-16T01:38:41.918678"
    },
    {
      "id": 16,
      "policy_name": "자립준비청년 자립수당 지원",
      "filename": "자립준비청년_자립수당_지원_2025051900",
      "policy_number": "20250519005400210856",
      "region": "서울",
      "category": "복지문화",
      "deadline": "상시",
      "summary": "ㅇ 자립준비청년에게 자립수당을 지급하여 보호종료 후 경제적 부담을 완화하고 복지향상을 통해 안정적인 사회 정착 및 성공적 자립 기여",
      "full_text": "서울\n복지문화\n상시\n\n공유하기\n인쇄\n스크랩\n자립준비청년 자립수당 지원\n최종 수정일2025년 6월 26일\n스크랩 수6\n조회수393\n태그\n#보조금\nㅇ 자립준비청년에게 자립수당을 지급하여 보호종료 후 경제적 부담을 완화하고 복지향상을 통해 안정적인 사회 정착 및 성공적 자립 기여\n\n한 눈에 보는 정책 요약\n한 눈에 보는 정책 요약 - 정책번호, 정책분야, 지원내용, 사업 운영 기간, 사업 신청기간, 지원 규모(명), 비고\n정책번호\n20250519005400210856\n정책분야\n복지문화\n지원내용\nㅇ (사업 근거)\n- 아동복지법 제38조제1항제1의2(자립에 필요한 자립정착금 및 자립수당 지급)\n\nㅇ (추진 경과)\n- 2019. 4. 보건복지부 시범사업 실시\n- 2021. 7. 지원대상, 지원기간 확대(’17.5월 이후 자립준비청년, 3년 → 18.8월 이후 자립준비청년, 5년)※ 보건복지부 자립준비청년 지원강화 방안(‘21.7.13)\n- 2022. 8. 자립수당 월 30만원 → 월 35만원 증액\n- 2023. 1. 자립수당 월 35만원 → 월 40만원 증액\n- 2024. 1. 자립수당 월 40만원 → 월 50만원 증액\n\nㅇ (사업 기간) ‘19년~\n\nㅇ (사업 대상)\n- (연령 기준) 보호종료 5년 이내 자립준비청년\n· 만 18세 이후 만기 또는 연장 보호종료된 자(단, ’18.8월 이후 보호종료된 자)\n· 만 15세 이후 보호조치가 조기 종료된 자로서 만 18세가 된 자\n\n- (기타 조건)\n· 보호종료일을 기준으로, 과거 2년 이상 연속하여 보호를 받은 자\n\nㅇ (사업 내용)\n- 방문·우편·온라인 신청 시, 자치구에서 지급결정하여 매월 50만원 지급(최대 60개월)\n\nㅇ (사업비) 8,464백만원 (국비 4,232백만원, 지방비 4,232백만원)\n사업 운영 기간\n2025년 1월 1일 ~ 2025년 12월 31일\n사업 신청기간\n상시\n지원 규모(명)\n0명\n신청자격\n신청자격 - 연령, 거주지역, 소득, 학력, 전공, 취업상태, 특화분야, 추가사항, 참여제한 대상\n연령\n만 15세~만 23세\n거주지역\n서울특별시 종로구, 서울특별시 중구, 서울특별시 용산구, 서울특별시 성동구, 서울특별시 광진구, 서울특별시 동대문구, 서울특별시 중랑구, 서울특별시 성북구, 서울특별시 강북구, 서울특별시 도봉구, 서울특별시 노원구, 서울특별시 은평구, 서울특별시 서대문구, 서울특별시 마포구, 서울특별시 양천구, 서울특별시 강서구, 서울특별시 구로구, 서울특별시 금천구, 서울특별시 영등포구, 서울특별시 동작구, 서울특별시 관악구, 서울특별시 서초구, 서울특별시 강남구, 서울특별시 송파구, 서울특별시 강동구\n소득\n무관\n학력\n제한없음\n전공\n제한없음\n취업상태\n제한없음\n특화분야\n기타\n추가사항\n참여제한 대상\n신청방법\n신청방법 - 신청절차, 심사 및 발표, 신청 사이트, 제출 서류\n신청절차\n심사 및 발표\n신청 사이트\n제출 서류\n기타\n기타 - 기타 정보, 주관 기관, 운영 기관, 참고사이트1, 참고사이트2\n기타 정보\n주관 기관\n아동담당관\n운영 기관\n참고사이트 1\n참고사이트 2\n정보 변경 내역",
      "operation_period": "2025년 1월 1일 ~ 2025년 12월 31일",
      "application_period": "상시",
      "support_content": "ㅇ (사업 근거) - 아동복지법 제38조제1항제1의2(자립에 필요한 자립정착금 및 자립수당 지급) ㅇ (추진 경과) - 2019. 4. 보건복지부 시범사업 실시 - 2021. 7. 지원대상, 지원기간 확대(’17.5월 이후 자립준비청년, 3년 → 18.8월 이후 자립준비청년, 5년)※ 보건복지부 자립준비청년 지원강화 방안(‘21.7.13) - 2022. 8. 자립수당 월 30만원 → 월 35만원 증액 - 2023. 1. 자립수당 월 35만원 → 월 40만원 증액 - 2024. 1. 자립수당 월 40만원 → 월 50만원 증액 ㅇ (사업 기간) ‘19년~ ㅇ (사업 대상) - (연령 기준) 보호종료 5년 이내 자립준비청년 · 만 18세 이후 만기 또는 연장 보호종료된 자(단, ’18.8월 이후 보호종료된 자) · 만 15세 이후 보호조치가 조기 종료된 자로서 만 18세가 된 자 - (기타 조건) · 보호종료일을 기준으로, 과거 2년 이상 연속하여 보호를 받은 자 ㅇ (사업 내용) - 방문·우편·온라인 신청 시, 자치구에서 지급결정하여 매월 50만원 지급(최대 60개월) ㅇ (사업비) 8,464백만원 (국비 4,232백만원, 지방비 4,232백만원)",
      "support_scale": null,
      "eligibility": {
        "age": {
          "max": 23,
          "min": 15,
          "description": "만 15세~만 23세"
        },
        "income": {
          "description": "무관"
        },
        "region": [
          "서울특별시 종로구, 서울특별시 중구, 서울특별시 용산구, 서울특별시 성동구, 서울특별시 광진구, 서울특별시 동대문구, 서울특별시 중랑구, 서울특별시 성북구, 서울특별시 강북구, 서울특별시 도봉구, 서울특별시 노원구, 서울특별시 은평구, 서울특별시 서대문구, 서울특별시 마포구, 서울특별시 양천구, 서울특별시 강서구, 서울특별시 구로구, 서울특별시 금천구, 서울특별시 영등포구, 서울특별시 동작구, 서울특별시 관악구, 서울특별시 서초구, 서울특별시 강남구, 서울특별시 송파구, 서울특별시 강동구"
        ]
      },
      "application_info": {
        "managing_agency": "아동담당관",
        "operating_agency": "참고사이트 1"
      },
      "additional_info": {},
      "required_documents": [],
      "created_at": "2025-11-16T01:38:41.920209",
      "updated_at": "2025-11-16T01:38:41.920209"
    },
    {
      "id": 17,
      "policy_name": "자립준비청년 자립지원 사업",
      "filename": "자립준비청년_자립지원_사업_2025061700",
      "policy_number": "20250617005400110944",
      "region": "전국",
      "category": "복지문화",
      "deadline": "상시",
      "summary": "아동복지시설(아동양육시설,공동생활가정), 가정위탁 보호대상 아동이 보호종료된 후에 사후 관리 및 개인별 맞춤형 사례관리 지원",
      "full_text": "전국\n복지문화\n상시\n\n공유하기\n인쇄\n스크랩\n자립준비청년 자립지원 사업\n최종 수정일2025년 6월 26일\n스크랩 수6\n조회수280\n태그\n#맞춤형상담서비스\n아동복지시설(아동양육시설,공동생활가정), 가정위탁 보호대상 아동이 보호종료된 후에 사후 관리 및 개인별 맞춤형 사례관리 지원\n\n한 눈에 보는 정책 요약\n한 눈에 보는 정책 요약 - 정책번호, 정책분야, 지원내용, 사업 운영 기간, 사업 신청기간, 지원 규모(명), 비고\n정책번호\n20250617005400110944\n정책분야\n복지문화\n지원내용\n자립준비청년의 안정적 사회정착 지원을 위해 보호종료 5년이내 자립준비청년을 대상으로 정기적 사후관리 상담 및 개인별 맞춤형 사례관리 서비스 지원\n사업 운영 기간\n상시\n사업 신청기간\n상시\n지원 규모(명)\n제한없음\n신청자격\n신청자격 - 연령, 거주지역, 소득, 학력, 전공, 취업상태, 특화분야, 추가사항, 참여제한 대상\n연령\n만 18세~만 29세\n거주지역\n전국\n소득\n무관\n학력\n제한없음\n전공\n제한없음\n취업상태\n제한없음\n특화분야\n기타\n추가사항\n- 아동복지시설, 가정위탁 보호종료 5년 이내 자립준비청년(18세 또는 연장 보호종료된 경우 보호종료로부터 5년간 지원)\n- 15세 이후 조기 보호종료된 경우 18세가 된 때로부터 5년간 지원(단, 개정된 아동복지법 시행일('24.2.9.)이후 18세가 된 자부터 적용)\n- 재보호조치 대상자로 결정 후 재보호조치 종료된 경우, 5년 중 재보호조치 결정 이전 동안 진행된 사후관리 기간을 제외한 잔여기간 지원\n참여제한 대상\n신청방법\n신청방법 - 신청절차, 심사 및 발표, 신청 사이트, 제출 서류\n신청절차\n심사 및 발표\n신청 사이트\n제출 서류\n기타\n기타 - 기타 정보, 주관 기관, 운영 기관, 참고사이트1, 참고사이트2\n기타 정보\n주관 기관\n인구아동정책관\n운영 기관\n참고사이트 1\n참고사이트 2\n정보 변경 내역\n정보 변경 내역 표로 변경일자, 변경 내용으로 구성되어있음\n변경일자\t변경 내용\n2025.06.26\t최종 수정일\n2025.06.17\t최초 등록일",
      "operation_period": "상시",
      "application_period": "상시",
      "support_content": "자립준비청년의 안정적 사회정착 지원을 위해 보호종료 5년이내 자립준비청년을 대상으로 정기적 사후관리 상담 및 개인별 맞춤형 사례관리 서비스 지원",
      "support_scale": null,
      "eligibility": {
        "age": {
          "max": 29,
          "min": 18,
          "description": "만 18세~만 29세"
        },
        "income": {
          "description": "무관"
        },
        "region": ["전국"]
      },
      "application_info": {
        "managing_agency": "인구아동정책관",
        "operating_agency": "참고사이트 1"
      },
      "additional_info": {},
      "required_documents": [],
      "created_at": "2025-11-16T01:38:41.922224",
      "updated_at": "2025-11-16T01:38:41.922224"
    },
    {
      "id": 18,
      "policy_name": "제대군인 전직지원금",
      "filename": "제대군인_전직지원금_2025011000",
      "policy_number": "20250110005400110151",
      "region": "전국",
      "category": "일자리",
      "deadline": "상시",
      "summary": "#맞춤형상담서비스",
      "full_text": "전국\n일자리\n상시\n\n공유하기\n인쇄\n스크랩\n제대군인 전직지원금\n최종 수정일2025년 1월 15일\n스크랩 수8\n조회수961\n태그\n#바우처\n#맞춤형상담서비스\n전역후 6개월 이내 실업상태의 군인연금비대상 장기복무제대군인의 취, 창업 촉진을 위한 전직지원금 지원\n\n한 눈에 보는 정책 요약\n한 눈에 보는 정책 요약 - 정책번호, 정책분야, 지원내용, 사업 운영 기간, 사업 신청기간, 지원 규모(명), 비고\n정책번호\n20250110005400110151\n정책분야\n일자리\n지원내용\n○ 매월 장기복무 81만 원, 중기복무 58만 원 씩 6개월 간 지급. 다만 수급기간 중 취창업시에는 취업이나 창업을 한 다음 달부터 남은 달까지 받을 총 지급액의 1/2을 일시금으로 지급\n* 신청기간 : 전역후 6개월이내\n사업 운영 기간\n상시\n사업 신청기간\n상시\n지원 규모(명)\n제한없음\n신청자격\n신청자격 - 연령, 거주지역, 소득, 학력, 전공, 취업상태, 특화분야, 추가사항, 참여제한 대상\n연령\n제한없음\n거주지역\n전국\n소득\n무관\n학력\n제한없음\n전공\n제한없음\n취업상태\n미취업자\n특화분야\n군인\n추가사항\n○ 지급 중단 사유\n- 적극적으로 구직활동을 하지 않은 경우(본인의 질병·부상·임신·출산 및 천재지변의 경우는 제외)\n- 거짓이나 그 밖의 부정한 방법으로 전직지원금을 지급받았거나 지급받으려 한 경우\n참여제한 대상\n* 군인연금 수령자는 제외\n신청방법\n신청방법 - 신청절차, 심사 및 발표, 신청 사이트, 제출 서류\n신청절차\n- 제대군인지원센터에 방문하거나 온라인, 우편으로 신청\n심사 및 발표\n신청 이후 약 25일 소요\n신청 사이트\nhttps://www.gov.kr/mw/AA020InfoCappView.do?CappBizCD=11800000096\n제출 서류\n전직지원급지급신청서, 개인정보 이용·제공 사전 동의서, 매월 1회 이상 적극적 구직활동 증명서류(해당장에 한함)\n기타\n기타 - 기타 정보, 주관 기관, 운영 기관, 참고사이트1, 참고사이트2\n기타 정보\n전국제대군인지원센터 (1666-9279)\n주관 기관\n국가보훈부\n운영 기관\n참고사이트 1\nhttps://www.vnet.go.kr/gud/GudCv002.do\n참고사이트 2\n정보 변경 내역\n정보 변경 내역 표로 변경일자, 변경 내용으로 구성되어있음\n변경일자\t변경 내용\n2025.01.15\t최종 수정일\n2025.01.10\t최초 등록일",
      "operation_period": "상시",
      "application_period": "상시",
      "support_content": "○ 매월 장기복무 81만 원, 중기복무 58만 원 씩 6개월 간 지급. 다만 수급기간 중 취창업시에는 취업이나 창업을 한 다음 달부터 남은 달까지 받을 총 지급액의 1/2을 일시금으로 지급 * 신청기간 : 전역후 6개월이내",
      "support_scale": null,
      "eligibility": {
        "income": {
          "description": "무관"
        },
        "region": ["전국"]
      },
      "application_info": {
        "application_url": "https://www.vnet.go.kr/gud/GudCv002.do",
        "managing_agency": "국가보훈부",
        "operating_agency": "참고사이트 1"
      },
      "additional_info": {},
      "required_documents": [],
      "created_at": "2025-11-16T01:38:41.924577",
      "updated_at": "2025-11-16T01:38:41.924577"
    },
    {
      "id": 19,
      "policy_name": "조기재취업수당",
      "filename": "조기재취업수당_2025021200",
      "policy_number": "20250212005400110432",
      "region": "전국",
      "category": "일자리",
      "deadline": "상시",
      "summary": "구직급여 수급자격자가 실업의 신고일로부터 14일이 지난 후 재취업한 날의 전날을 기준으로 소정급여일수를 1/2 이상 남기고 재취업한 경우, 12개월 이상 계속 고용되거나 또는 사업을 영위한 경우에 남아 있는 구직급여의 1/2을 조기재취업수당으로 지급하여 구직급여 수급자의 빠른 재취업을 촉진하는 제도",
      "full_text": "전국\n일자리\n상시\n\n공유하기\n인쇄\n스크랩\n조기재취업수당\n최종 수정일2025년 2월 26일\n스크랩 수34\n조회수3400\n태그\n#보조금\n구직급여 수급자격자가 실업의 신고일로부터 14일이 지난 후 재취업한 날의 전날을 기준으로 소정급여일수를 1/2 이상 남기고 재취업한 경우, 12개월 이상 계속 고용되거나 또는 사업을 영위한 경우에 남아 있는 구직급여의 1/2을 조기재취업수당으로 지급하여 구직급여 수급자의 빠른 재취업을 촉진하는 제도\n\n한 눈에 보는 정책 요약\n한 눈에 보는 정책 요약 - 정책번호, 정책분야, 지원내용, 사업 운영 기간, 사업 신청기간, 지원 규모(명), 비고\n정책번호\n20250212005400110432\n정책분야\n일자리\n지원내용\n지급기준\n- 재취업한 날의 전날을 기준으로 소정급여일수를 1/2 이상 남기고 재취업한 경우, 12개월 이상 계속하여 고용되거나 또는 사업을 영위한 경우에 남아 있는 구직급여의 1/2을 조기재취업수당으로 지급\n사업 운영 기간\n상시\n사업 신청기간\n상시\n지원 규모(명)\n제한없음\n신청자격\n신청자격 - 연령, 거주지역, 소득, 학력, 전공, 취업상태, 특화분야, 추가사항, 참여제한 대상\n연령\n제한없음\n거주지역\n전국\n소득\n무관\n학력\n제한없음\n전공\n제한없음\n취업상태\n제한없음\n특화분야\n제한없음\n추가사항\n지급요건: 아래 요건 모두 충족\n1) 재취업한 날의 전날을 기준으로 고용보험법 제50조에 따른 소정급여일수를 2분의 1이상 남긴 상태여야 함\n2) 12개월 이상 계속하여 고용된(또는 사업을 영위한) 경우\n- 사업주가 변경되더라도 기간의 단절 없이 계속 고용되어 12개월 이상 근무한 경우이어야 함\n* (건설)일용근로자로 재취업한 경우에도 재취업한 날부터 매달 10일 이상 일용근로한 달이 12개월 이상이어야 함\n3. 지급 제외 요건\n- 최후 이직한 사업의 사업주에게 재고용된 경우\n- 최후 이직한 사업의 사업주와 관련된 사업주로서 최종 이직 당시의 사업주와 합병·분할되거나 그 사업을 넘겨받은 사업주에게 재고용된 경우\n- 실업 신고일 이전 채용을 약속한 사업주에게 고용된 경우\n- 고용노동부 장관이 고시한 임금액 이상인 직장에 취직한 경우(‘25년 고시 월 임금액: 5,740,000원)\n- 국가공무원법 및 지방공무원법에 따른 공무원으로 임용된 경우(단, 별정직 또는 임기제 공무원 제외\n참여제한 대상\n자영업자, 예술인, 노무제공자로 수급자격 인정받은 수급자는 조기재취업수당 적용 제외\n신청방법\n신청방법 - 신청절차, 심사 및 발표, 신청 사이트, 제출 서류\n신청절차\n재취업한 날 또는 사업을 시작한 날부터 12개월이 경과한 이후 관할 고용센터(구직급여를 지급받았던 고용센터)에 조기재취업수당 청구서 및 관련 증빙서류 제출(사후지급)\n심사 및 발표\n심사 후 개별 발표\n신청 사이트\nhttps://www.work24.go.kr\n제출 서류\n- 조기재취업수당 청구서\n- (근로자) 수급자격증, 재직증명서 또는 근로계약서 등 12개월 이상 고용되었음을 증명하는 서류\n- (자영업자) 수급자격증, 사업설명서, 사무실 임대차계약서, 사업자등록증, 12개월간 매출증빙내역 등 사업을 개시 또는 영위하였음을 증명하는 서류\n- 기타 사실관계를 입증할 근거자료 등\n기타\n기타 - 기타 정보, 주관 기관, 운영 기관, 참고사이트1, 참고사이트2\n기타 정보\n주관 기관\n고용노동부\n운영 기관\n참고사이트 1\nhttps://www.work24.go.kr\n참고사이트 2\nhttps://www.work24.go.kr\n정보 변경 내역\n정보 변경 내역 표로 변경일자, 변경 내용으로 구성되어있음\n변경일자\t변경 내용\n2025.02.26\t최종 수정일\n2025.02.12\t최초 등록일",
      "operation_period": "상시",
      "application_period": "상시",
      "support_content": "지급기준 - 재취업한 날의 전날을 기준으로 소정급여일수를 1/2 이상 남기고 재취업한 경우, 12개월 이상 계속하여 고용되거나 또는 사업을 영위한 경우에 남아 있는 구직급여의 1/2을 조기재취업수당으로 지급",
      "support_scale": null,
      "eligibility": {
        "income": {
          "description": "무관"
        },
        "region": ["전국"]
      },
      "application_info": {
        "application_url": "https://www.work24.go.kr",
        "managing_agency": "고용노동부",
        "operating_agency": "참고사이트 1"
      },
      "additional_info": {},
      "required_documents": [],
      "created_at": "2025-11-16T01:38:41.926350",
      "updated_at": "2025-11-16T01:38:41.926350"
    },
    {
      "id": 20,
      "policy_name": "청년 국가기술자격시험 응시료 지원사업",
      "filename": "청년_국가기술자격시험_응시료_지원사업_2025020400",
      "policy_number": "20250204005400110409",
      "region": "전국",
      "category": "일자리",
      "deadline": "상시",
      "summary": "청년의 구직활동과 경력개발의 경제적 부담을 완화하기 위한 사업",
      "full_text": "전국\n일자리\n상시\n\n공유하기\n인쇄\n스크랩\n청년 국가기술자격시험 응시료 지원사업\n최종 수정일2025년 2월 7일\n스크랩 수880\n조회수44617\n태그\n#바우처\n청년의 구직활동과 경력개발의 경제적 부담을 완화하기 위한 사업\n\n한 눈에 보는 정책 요약\n한 눈에 보는 정책 요약 - 정책번호, 정책분야, 지원내용, 사업 운영 기간, 사업 신청기간, 지원 규모(명), 비고\n정책번호\n20250204005400110409\n정책분야\n일자리\n지원내용\n- 34세 이하 청년을 대상(소득 및 취업 여부 무관)으로 한국산업인력공단이 시행하는 국가기술자격 시험(‘25년 기준 488종목)에 응시하는 경우 응시료의 50%를 선 지원\n- 1인당 총 3회 지원으로 제한하고, 지원금 소진 시까지 한정\n사업 운영 기간\n상시\n사업 신청기간\n상시\n지원 규모(명)\n제한없음\n신청자격\n신청자격 - 연령, 거주지역, 소득, 학력, 전공, 취업상태, 특화분야, 추가사항, 참여제한 대상\n연령\n만 0세~만 34세\n거주지역\n전국\n소득\n무관\n학력\n제한없음\n전공\n제한없음\n취업상태\n제한없음\n특화분야\n제한없음\n추가사항\n34세 이하 청년, 한국산업인력공단 시행 국가기술자격 종목, 1인당 연간 3회 한도\n참여제한 대상\n신청방법\n신청방법 - 신청절차, 심사 및 발표, 신청 사이트, 제출 서류\n신청절차\n원서접수 시 응시료 지원받을 시험 선택 후 결제\n심사 및 발표\n신청 사이트\nhttps://www.q-net.or.kr/man001.do?gSite=Q\n제출 서류\n기타\n기타 - 기타 정보, 주관 기관, 운영 기관, 참고사이트1, 참고사이트2\n기타 정보\n1인당 지원한도는 연간 3회이며, 지원예산 소진시 잔여 지원횟수와 상관없이 신청이 불가\n(예산소진시 사전 공지 예정)\n주관 기관\n고용노동부\n운영 기관\n한국산업인력공단\n참고사이트 1\nhttps://www.q-net.or.kr/man004.do?id=man00402&gSite=Q&gId=\n참고사이트 2\n정보 변경 내역\n정보 변경 내역 표로 변경일자, 변경 내용으로 구성되어있음\n변경일자\t변경 내용\n2025.02.07\t최종 수정일\n2025.02.04\t최초 등록일",
      "operation_period": "상시",
      "application_period": "상시",
      "support_content": "- 34세 이하 청년을 대상(소득 및 취업 여부 무관)으로 한국산업인력공단이 시행하는 국가기술자격 시험(‘25년 기준 488종목)에 응시하는 경우 응시료의 50%를 선 지원 - 1인당 총 3회 지원으로 제한하고, 지원금 소진 시까지 한정",
      "support_scale": null,
      "eligibility": {
        "age": {
          "max": 34,
          "min": 0,
          "description": "만 0세~만 34세"
        },
        "income": {
          "description": "무관"
        },
        "region": ["전국"]
      },
      "application_info": {
        "application_url": "https://www.q-net.or.kr/man004.do?id=man00402&gSite=Q&gId=",
        "managing_agency": "고용노동부",
        "operating_agency": "한국산업인력공단"
      },
      "additional_info": {},
      "required_documents": [],
      "created_at": "2025-11-16T01:38:41.927878",
      "updated_at": "2025-11-16T01:38:41.927878"
    },
    {
      "id": 21,
      "policy_name": "청년 자산형성 지원(청년도약계좌)",
      "filename": "청년_자산형성_지원청년도약계좌_2025061800",
      "policy_number": "20250618005400111001",
      "region": "전국",
      "category": "복지문화",
      "deadline": "상시",
      "summary": "만기 5년 동안 매월 70만원 한도 내에서 자유롭게 납입 가능한 정부지원형 적금상품으로 청년의 중장기 자산형성을 지원합니다.",
      "full_text": "전국\n복지문화\n상시\n\n공유하기\n인쇄\n스크랩\n청년 자산형성 지원(청년도약계좌)\n최종 수정일2025년 6월 25일\n스크랩 수319\n조회수7209\n태그\n#보조금\n만기 5년 동안 매월 70만원 한도 내에서 자유롭게 납입 가능한 정부지원형 적금상품으로 청년의 중장기 자산형성을 지원합니다.\n\n한 눈에 보는 정책 요약\n한 눈에 보는 정책 요약 - 정책번호, 정책분야, 지원내용, 사업 운영 기간, 사업 신청기간, 지원 규모(명), 비고\n정책번호\n20250618005400111001\n정책분야\n복지문화\n지원내용\n□ 청년도약계좌는 매월 가입신청할 수 있도록 운영\n□ 가입자의 소득구간 및 월 납입액에 따라 최대 6%까지 정부기여금을 지원\n□ 본인이 납입한 금액에 비례하여 정부기여금 지원 및 이자소득 등에 대한 비과세 혜택(만기·특별중도해지시)\n※ 전년도 소득 확정 전, 가입자의 경우 모두 비과세 인정(24년 1월 이전에 가입하였더라도 해당)\n□ 저소득층 청년 대상 일정수준의 우대금리 제공 (명칭 : 소득+우대금리)\n※ 육아휴직급여(육아휴직수당 포함) 및 군장병급여만 있는 경우, 정부기여금 매칭비율 6% 적용\n사업 운영 기간\n2025년 1월 1일 ~ 2025년 12월 31일\n사업 신청기간\n상시\n지원 규모(명)\n0명\n신청자격\n신청자격 - 연령, 거주지역, 소득, 학력, 전공, 취업상태, 특화분야, 추가사항, 참여제한 대상\n연령\n만 19세~만 34세\n거주지역\n전국\n소득\n□ (개인소득요건) 직전 과세기간의 총급여액이 7,500만원 이하이며, 종합소득과세표준에 합산되는 종합소득금액이 6,300만원 이하인 경우 (단, 육아휴직급여(육아휴직수당), 군 장병급여 외에 비과세 소득만 있는 경우는 제외) ※ 직전 과세기간의 소득이 확정되지 않은 기간에 소득을 확인한 경우 전전년도 소득으로 인정 □ (가구소득요건) 가구원 수에 따른 기준 중위소득 250% 이하에 해당하는 자 ※ 직전 과세기간의 소득이 확정되지 않은 기간에 소득을 확인한 경우 전전년도 소득으로 인정 가구원은 청년 본인과 본인의 주민등록표 등본상 배우자, 부모, 자녀, 형제·자매(미성년자)를 기준으로 판단\n학력\n제한없음\n전공\n제한없음\n취업상태\n제한없음\n특화분야\n제한없음\n추가사항\n□ (금융소득종합과세) 가입일이 속한 과세기간의 직전 3개년도 중 1회 이상 금융소득종합과세 대상자에 해당하지 않는 자\n참여제한 대상\n현재 청년희망적금을 가입 유지하고 있는 경우 가입 불가능\n신청방법\n신청방법 - 신청절차, 심사 및 발표, 신청 사이트, 제출 서류\n신청절차\n[매월]\n가입신청 - 취급은행 앱\n[신청 후 약 2주]\n가입심사 - 서민금융진흥원\n[익월 초]\n계좌개설 - 취급은행 앱\n심사 및 발표\n□ 개인 및 가구소득 확인 세부 절차 (약 2주 소요)\n① 나이 및 개인소득 확인 → ② 가구원 확정 및 정보제공 동의 → ③ 가구소득 확인 → ④ 확인결과 통보\n※ 행정정보공동이용서비스를 통해 전면 비대면 확인 시행(행안부, 국세청, 병무청)\n□ 개인소득은 가입일로부터 1년 주기로 유지심사를 통해 현행화하여 기여금 지급여부 및 규모 조정\n신청 사이트\n제출 서류\n기타\n기타 - 기타 정보, 주관 기관, 운영 기관, 참고사이트1, 참고사이트2\n기타 정보\n□ 취급은행을 통틀어 1명당 1개의 계좌만 가입 가능\n※ 가입요건을 충족하는 가구(청년부부 등)일 경우 부부가 각각 가입 가능\n□ 복지, 고용지원 및 지자체 상품은 동시가입이 가능하나, 사업목적이 유사한 청년희망적금은 만기(또는 해지) 후 가입이 가능\n□ 청년내일저축계좌, 청년내일채움공제 등과 동시가입이 가능\n□ 가입일 현재 직전 과세기간의 금융소득종합과세가 확정되지 않아 전전 과세기간까지만 금융소득종합과세 대상 여부가 확인된 경우, 직전 과세기간의 금융소득종합과세 대상자로 확인되는 시점부터 납입중지\n「공공재정 부정청구 금지 및 부정이익 환수 등에 관한 법률」에 따른 부정이익으로 확인되는 경우 환수 등의 제재 가능\n□ 청년도약계좌 상품에 대한 보다 자세한 안내는 서민금융콜센터(1397 바로연결번호 3번)로 문의하거나 홈페이지 자주하는 질문 참고(참고사이트2)\n주관 기관\n금융위원회\n운영 기관\n서민금융진흥원\n참고사이트 1\nhttps://ylaccount.kinfa.or.kr\n참고사이트 2\nhttps://www.kinfa.or.kr/counselingSupport/oftendoneQuestion.do\n정보 변경 내역\n정보 변경 내역 표로 변경일자, 변경 내용으로 구성되어있음\n변경일자\t변경 내용\n2025.06.25\t최종 수정일\n2025.06.18\t최초 등록일",
      "operation_period": "2025년 1월 1일 ~ 2025년 12월 31일",
      "application_period": "상시",
      "support_content": "※ 전년도 소득 확정 전, 가입자의 경우 모두 비과세 인정(24년 1월 이전에 가입하였더라도 해당) ※ 육아휴직급여(육아휴직수당 포함) 및 군장병급여만 있는 경우, 정부기여금 매칭비율 6% 적용",
      "support_scale": null,
      "eligibility": {
        "age": {
          "max": 34,
          "min": 19,
          "description": "만 19세~만 34세"
        },
        "income": {
          "description": "□ (개인소득요건) 직전 과세기간의 총급여액이 7,500만원 이하이며, 종합소득과세표준에 합산되는 종합소득금액이 6,300만원 이하인 경우 (단, 육아휴직급여(육아휴직수당), 군 장병급여 외에 비과세 소득만 있는 경우는 제외) ※ 직전 과세기간의 소득이 확정되지 않은 기간에 소득을 확인한 경우 전전년도 소득으로 인정 □ (가구소득요건) 가구원 수에 따른 기준 중위소득 250% 이하에 해당하는 자 ※ 직전 과세기간의 소득이 확정되지 않은 기간에 소득을 확인한 경우 전전년도 소득으로 인정 가구원은 청년 본인과 본인의 주민등록표 등본상 배우자, 부모, 자녀, 형제·자매(미성년자)를 기준으로 판단"
        },
        "region": ["전국"]
      },
      "application_info": {
        "application_url": "https://www.kinfa.or.kr/counselingSupport/oftendoneQuestion.do",
        "managing_agency": "금융위원회",
        "operating_agency": "서민금융진흥원"
      },
      "additional_info": {},
      "required_documents": [
        {
          "id": 1,
          "name": "신분증",
          "notes": "사본 가능",
          "description": "주민등록증 또는 운전면허증",
          "is_required": true,
          "issue_location": "주민센터 또는 경찰서"
        },
        {
          "id": 2,
          "name": "소득증빙서류",
          "notes": "최근 1년치",
          "description": "근로소득 원천징수영수증 또는 소득금액증명원",
          "is_required": true,
          "issue_location": "국세청 홈택스"
        },
        {
          "id": 3,
          "name": "통장사본",
          "notes": null,
          "description": "본인 명의 계좌",
          "is_required": true,
          "issue_location": "해당 은행"
        }
      ],
      "created_at": "2025-11-16T01:38:41.930895",
      "updated_at": "2025-11-16T01:38:41.930895"
    },
    {
      "id": 22,
      "policy_name": "청년 주택드림 디딤돌 대출",
      "filename": "청년_주택드림_디딤돌_대출_2025051400",
      "policy_number": "20250514005400110811",
      "region": "전국",
      "category": "주거",
      "deadline": "상시",
      "summary": "청년의 주거사다리 지원을 위해 청년 주택드림 통장으로 청약 당첨 시 주택구입자금을 대출",
      "full_text": "전국\n주거\n상시\n\n공유하기\n인쇄\n스크랩\n청년 주택드림 디딤돌 대출\n최종 수정일2025년 5월 14일\n스크랩 수294\n조회수9852\n태그\n#대출\n청년의 주거사다리 지원을 위해 청년 주택드림 통장으로 청약 당첨 시 주택구입자금을 대출\n\n한 눈에 보는 정책 요약\n한 눈에 보는 정책 요약 - 정책번호, 정책분야, 지원내용, 사업 운영 기간, 사업 신청기간, 지원 규모(명), 비고\n정책번호\n20250514005400110811\n정책분야\n주거\n지원내용\n□ 대출금리 : 2.4% ~ 4.15%\n□ 대출한도 : 다음 중 작은 금액으로 산정\n- 미혼 3억원, 신혼 4억원 이내(LTV 70%, 생애최초 주택구입자는 LTV 80%, DTI 60% 이내)\n- 분양가격 이내로 하되, 대출총액은 (본건 내집마련 디딤돌 대출 + 국민주택건설자금 + 중도금대출 + 기금대출)은 매매가격 초과 불가\n- 대출금액 = [(담보주택 평가액 × LTV) – 선순위채권 – 임대보증금 및 최우선변제소액임차보증금]\n□ 대출기간 : 10년, 15년, 20년, 30년(연소득 4천만원 이하는 만기 40년 이용 가능)(거치 1년 또는 비거치)\n사업 운영 기간\n상시\n사업 신청기간\n상시\n지원 규모(명)\n0명\n신청자격\n신청자격 - 연령, 거주지역, 소득, 학력, 전공, 취업상태, 특화분야, 추가사항, 참여제한 대상\n연령\n만 0세~만 39세\n거주지역\n전국\n소득\n연소득 0만원 이상 ~ 7000만원 이하\n학력\n제한없음\n전공\n제한없음\n취업상태\n제한없음\n특화분야\n제한없음\n추가사항\n대출 대상주택*을 구입하고자 하는 자로서 아래의 요건을 모두 충족하는 자\n* 대상주택 : 주거 전용면적이 85㎡(수도권을 제외한 도시지역이 아닌 읍 또는 면 지역 100㎡) 이하 주택으로, 대출 접수일 현재 담보주택의 평가액이 6억원 이하인 주택\n\n□ 청년 주택드림 통장 청약 당첨자\n입주자모집공고일 이전 보유한 청년 주택드림 통장으로 청약 당첨(당첨시 만39세 이하)되어 분양계약을 체결하고,\n아래 조건을 모두 충족하여 청년 주택드림 통장과 연계하여 디딤돌 대출을 신청하는 자 (상속, 증여, 재산분할로 주택을 취득하는 경우 불가)\n\n가. 청년 주택드림 통장 가입일(전환일)로부터 대출접수일까지 1년 이상 가입\n나. 대출접수일 기준 1천만원 이상 납입\n(단, 월 납입실적은 최대 100만원까지만 인정하며, 담보목적물(해당주택)의 계약금 납입 목적으로 1회에 한하여 청년 주택드림 통장 납입금액을 인출한 경우에는 대출접수일 기준 1천만원 이상 잔고가 확인되어야 함)\n\n<청년 주택드림 통장 월 납입실적 예외사항>\n(1) 후분양 등의 사유로 월 100만원 납입만으로는 1천만원 이상 납입요건 충족이 어려운 경우 부족분만큼 대출 신청 전 일시납하는 금액 인정\n(2) 종합저축에서 청년 주택드림 통장으로 전환가입한 경우 기존 통장의 잔고는 최대 500만원까지 인정(단, 청년우대형 종합저축에서 청년 주택드림 통장으로 전환된 경우 기존 잔고 모두 인정)\n(3) 청년도약계좌, 청년희망적금, 군장병 내일적금 등 만기 일시납액을 청년 주택드림 통장으로 예치한 경우 최대 500만원까지 인정\n(4) 이 기준에서 달리 정하고 있지 않은 사항에 대해서는 별도로 정한 지침에 따름\n\n□ 세대주 : 대출접수일 현재 민법상 성년인 세대주\n\n□ 무주택 : 세대주를 포함한 세대원 전원이 무주택인 자\n- 분양권 및 조합원 입주권도 주택 보유로 간주\n\n□ 중복대출 금지 : 주택도시기금대출 및 은행재원 주택담보대출 미이용자 등\n- (주택도시기금대출) 성년인 세대원 전원이 기금 대출을 이용 중이면 대출 불가\n단, 기금의 전세자금 대출을 받은 경우에는 실행일 당일 상환조건부로 대출 가능\n- (주택담보대출) 차주 및 배우자(결혼예정 또는 분리된 배우자 포함)가 다른 목적물로 주택담보(중도금)대출을 이용 중이면 대출 불가\n\n□ 소득 : 미혼인 경우 연간 총소득 7천만원, 신혼가구인 경우 대출신청인과 배우자의 합산 총소득이 연간 1억원 이하인 자\n\n□ 자산 : 대출신청인 및 배우자의 합산 순자산 가액이 통계청에서 발표하는 최근년도 가계금융복지조사의 ‘소득 5분위별 자산 및 부채현황’ 중 소득 4분위 전체가구 평균값 이하(십만원 단위에서 반올림)인 자→2025년도 기준 4.88억원\n\n□ 신용도 : 아래 요건을 모두 충족하는 자\n- 신용정보회사의 개인신용평가가 일정점수 이상인 경우\n- 신청인이 한국신용정보원 “신용정보관리규약”에서 정하는 아래의 신용정보 및 해제 정보가 남아있는 경우 대출 불가능\n1) 연체, 대위변제·대지급, 부도, 관련인 정보\n2) 금융질서문란정보, 공공기록정보, 특수기록정보\n3) 신용회복지원등록정보\n- 그 외, 부부에 대하여 대출취급기관 내규로 대출을 제한하고 있는 경우에는 대출 불가능\n참여제한 대상\n신청방법\n신청방법 - 신청절차, 심사 및 발표, 신청 사이트, 제출 서류\n신청절차\n□ 신청시기 : 소유권이전등기를 하기 전에 신청. 단, 소유권이전등기를 한 경우에는 이전등기 접수일로부터 3개월 이내까지 신청\n□ 신청방법\n○ 온라인 신청 : 기금e든든 홈페이지(https://enhuf.molit.go.kr)\n- 이용 가능 은행 : 우리, 신한, 국민, 농협, 하나은행\n○ 은행 방문 신청 : 기금 수탁은행인 우리, 신한, 국민, 농협, 하나은행에서 가능\n- 이용 가능 지점은 은행 상황에 따라 다를 수 있습니다.\n심사 및 발표\n자산심사 관련 자세한 사항은 기금포탈 [고객서비스]-[자산심사 및 금리안내]-[자산 심사 안내]*를 참고\n* https://nhuf.molit.go.kr/FP/FP08/FP0813/FP081301.jsp?id=20&mode=S¤tPage=1&articleId=1160\n신청 사이트\nhttps://enhuf.molit.go.kr\n제출 서류\n□ 본인 확인 서류 : 주민등록증, 운전면허증, 여권 중 택1\n□ 대상자확인 : 주민등록등본(1개월 이내 발급분)\n가. 배우자 분리세대 : 가족관계증명원(1개월 이내 발급분)\n나. 배우자 외국인, 재외국민 또는 외국국적동포 : 외국인등록증 또는 국내거소신고사실증명\n다. 결혼예정자 : 예식장계약서 또는 청첩장\n\n□ 재직 및 사업영위 확인 : 건강보험자격득실 확인서\n가. 재직시 : 필요시 사업자등록증이 첨부된 재직증명서\n나. 사업영위시 : 사업자등록증\n상기와 같은 방법으로 확인이 불가능한 경우에는 경력증명서, 위촉증명서, 고용계약서 등 이와 유사한 형태의 계약서 등\n\n□ 소득확인 : 소득구분별 아래의 서류\n가. 근로소득(아래 서류 중 택1)\n- 세무서(홈텍스)발급 소득금액증명원 또는 ISA 가입용 소득확인증명서\n- 연말정산용 원천징수영수증(원천징수부 등 포함)\n- 급여내역이 포함된 증명서(재직회사가 확인날인한 급여명세표, 임금대장, 갑근세 원천징수 확인서, 일용근로소득지급명세서)\n\n나. 사업소득(아래 서류 중 택1)\n- 세무서(홈텍스)발급 소득금액증명원 또는 ISA 가입용 소득확인증명서\n- 사업소득 원천징수영수증(연말정산용)\n- 세무사가 확인한 전년도 과세표준확정신고 및 납부 계산서\n\n다. 연금소득 : 연금수급권자확인서 등 기타 연금수령을 확인할 수 있는 지급기관 증명서 (연금수령액이 표기되지 않은 경우 연금수령 통장)\n\n라. 기타소득 : 세무서(홈텍스)발급 소득금액증명원\n\n마. 무소득 : 신고사실없음 사실증명원\n\n바. 소득 추정 시 : 최근 2개년도 건강보험/국민연금 납부확인서\n\n□ 주택 관련 서류\n가. 분양계약서, 인감증명서\n\n나. 등기권리증(소유권 이전 후 대출 취급 시)\n\n다. 청약당첨사실확인서\n\n라. 청약통장 거래내역서 등 청년 주택드림 디딤돌 대출 청약요건 확인 가능서류\n\n마. 아파트 등기사항전부증명서(이전등기 전의 경우 생략 가능)\n\n바. 임대차 있는 경우 : 임대차계약서\n\n기타 심사 시 필요한 서류 추가 징구 가능\n기타\n기타 - 기타 정보, 주관 기관, 운영 기관, 참고사이트1, 참고사이트2\n기타 정보\n□ 대출 심사 관련한 상담 : 주택도시보증공사 콜센터 1566-9009 및 기금 수탁은행 지점\n□ 자산 심사 관련한 상담 : 자산심사 전용 상담센터 1551-3119 및 심사 진행 중 안내된 담당자 번호\n주관 기관\n국토교통부\n운영 기관\n참고사이트 1\nhttps://nhuf.molit.go.kr/FP/FP05/FP0503/FP05030901.jsp\n참고사이트 2\n정보 변경 내역\n정보 변경 내역 표로 변경일자, 변경 내용으로 구성되어있음\n변경일자\t변경 내용\n2025.05.14\t최종 수정일\n2025.05.14\t최초 등록일",
      "operation_period": "상시",
      "application_period": "상시",
      "support_content": "- 미혼 3억원, 신혼 4억원 이내(LTV 70%, 생애최초 주택구입자는 LTV 80%, DTI 60% 이내) - 분양가격 이내로 하되, 대출총액은 (본건 내집마련 디딤돌 대출 + 국민주택건설자금 + 중도금대출 + 기금대출)은 매매가격 초과 불가 - 대출금액 = [(담보주택 평가액 × LTV) – 선순위채권 – 임대보증금 및 최우선변제소액임차보증금]",
      "support_scale": null,
      "eligibility": {
        "age": {
          "max": 39,
          "min": 0,
          "description": "만 0세~만 39세"
        },
        "income": {
          "description": "연소득 0만원 이상 ~ 7000만원 이하"
        },
        "region": ["전국"]
      },
      "application_info": {
        "application_url": "https://nhuf.molit.go.kr/FP/FP05/FP0503/FP05030901.jsp",
        "managing_agency": "국토교통부",
        "operating_agency": "참고사이트 1"
      },
      "additional_info": {},
      "required_documents": [],
      "created_at": "2025-11-16T01:38:41.933173",
      "updated_at": "2025-11-16T01:38:41.933173"
    },
    {
      "id": 23,
      "policy_name": "청년도전지원사업",
      "filename": "청년도전지원사업_2025012200",
      "policy_number": "20250122005400110346",
      "region": "전국",
      "category": "일자리",
      "deadline": "상시",
      "summary": "#장기미취업청년",
      "full_text": "전국\n일자리\n상시\n\n공유하기\n인쇄\n스크랩\n청년도전지원사업\n최종 수정일2025년 1월 22일\n스크랩 수461\n조회수44646\n태그\n#보조금\n#장기미취업청년\n구직단념청년 등에게 구직의욕 고취 및 자신감 강화를 위한 맞춤형 프로그램 제공, 참여자에게 참여수당.인센티브 지급\n\n한 눈에 보는 정책 요약\n한 눈에 보는 정책 요약 - 정책번호, 정책분야, 지원내용, 사업 운영 기간, 사업 신청기간, 지원 규모(명), 비고\n정책번호\n20250122005400110346\n정책분야\n일자리\n지원내용\n□ 단기프로그램\nㅇ 사업운영기간: 5주 이상\nㅇ 참여수당: 1인당 50만원\nㅇ 이수 인센티브, 취업 인센티브: 없음\n\n□ 중기 프로그램\nㅇ 사업운영기간: 15주 이상\nㅇ 참여수당: 1인당 150만원(50만원x3회)\nㅇ 이수 인센티브: 이수 시 20만원\nㅇ취업 인센티브: 이수 후 6개월 이내 취업하고 3개월 근속 시 50만원\n\n□ 장기 프로그램\nㅇ 사업운영기간: 25주 이상\nㅇ 참여수당: 1인당 250만원(50만원×5회)\nㅇ 이수 인센티브: 이수 시 20만원, 취업관련 활동 시 30만원(국취Ⅰ유형은 국취참여수당으로 대체)\nㅇ취업 인센티브: 이수 후 6개월 이내 취업하고 3개월 근속 시 50만원\n사업 운영 기간\n사업 운영기간: 단기 프로그램 5주 이상, 중기 프로그램 15주 이상, 장기 프로그램 25주 이상\n사업 신청기간\n상시\n지원 규모(명)\n0명\n신청자격\n신청자격 - 연령, 거주지역, 소득, 학력, 전공, 취업상태, 특화분야, 추가사항, 참여제한 대상\n연령\n제한없음\n거주지역\n전국\n소득\n무관\n학력\n제한없음\n전공\n제한없음\n취업상태\n제한없음\n특화분야\n제한없음\n추가사항\n□ (구직단념청년) 사업 신청일 이전 6개월 이상 취업.교육.직업훈련 참여 이력이 없고*, 구직단념청년 상담원 문답표(붙임 1) 21점 이상(30점 만점)인 만 18~34세 청년\n* 취업은 고용보험DB 상용직 기준, 교육.직업훈련은 HRD-Net 기준으로 자격 확인\n※ 다만, 고등학교 졸업 또는 졸업 예정자로 상급학교에 진학하지 않거나, 취업 의지가 낮은 자는 사업 신청일 이전 6개월 이상 취업.교육.직업훈련 참여 이력이 있어도 참여 가능\n※ 6개월 이내 의무복무 예정자 또는 군인(사회복무요원) 참여 불가\n※ 군 경력자는 복무기간에 비례하여 참여 제한 연령을 연동하여 적용(최고 만 39세로 한정)\n\n□ (자립준비청년*) 아동복지시설 등**에서 보호받고 퇴소한 자 중 퇴소 5년 이내의 청년 또는 퇴소 대상자임에도 불구하고 퇴소일을연장한 만 18~34세 청년\n* 「보호종료아동 지원강화 방안(′21.7)」에 따라 향후 보호종료아동의 명칭을 ‘자립준비청년’ 등으로 변경\n** 아동양육시설, 공동생활가정, 가정위탁, 아동보호치료시설, 자립지원시설 등\n\n□ (청소년복지시설 입.퇴소 청년) ?청소년복지 지원법? 제31조에 따른 청소년복지시설*에서 보호한 만 18~34세 청년\n* 청소년쉼터, 청소년자립지원관, 청소년회복지원시설 등\n\n□ (북한 이탈 청년) 북한을 이탈한 자*로서 만 18~34세 청년\n* 군사분계선 이북지역(“북한”)에 주소, 직계가족, 배우자, 직장 등을 두고 있는 자로서 북한을 벗어난 후 외국 국적을 취득하지 아니한 사람\n\n□ (지역특화청년) 위 참여자에 해당하지 않는 청년 또는 지자체 조례 등에서 지원의 필요성이 있다고 인정하는 청년(단기, 중기, 장기 프로그램별 참여인원의 최대 30%까지 참여 가능)\n※ 사업계획 수립 시 지역특화의 기준을 작성?제출하고 심사 시 적정성 여부를 확인 및 보완하며, 추후 주요 내용 변경 시 고용노동(지)청에 변경 승인을 받아 운영\n참여제한 대상\n□ (공통) 참여자에 해당하더라도 다음의 어느 하나에 해당하는 자는 청년도전지원사업 참여를 제한\nㅇ고용보험법에 따른 구직급여를 받고 있거나 구직급여의 지급이 끝난 날부터 6개월이 지나지 아니한 자*\n* 다만, 고용보험에 가입되어 구직급여 수급자격을 갖춘 경우라도 구직급여를 수급하지 않으면 참여 가능\nㅇ 국민취업지원제도에 참여하여 수혜 중인 자\nㅇ 사이버대학교, 대학원, 방송통신고등(대)학교 등 재학생\n\n□ (단기 프로그램) 참여요건 충족 시 재참여 가능(이수자 재참여 시 참여수당 등 중복지급 불가)\n참여요건 충족 시 재참여 가능(이수자 재참여 시 참여수당 등 중복지급 불가)\nㅇ 단기 프로그램 참여 후 종료된 자는 종료일로부터 6개월 경과 후에 중기.장기 프로그램 참여 가능(단, 당해연도 중복 참여 불가)\n※ 중기, 장기 프로그램 이수자는 단기프로그램 재참여 불가\n\n□ (중장기 프로그램) 국가 또는 지자체의 유사사업에 참여하여 수당* 등을 지원받은 자로서 수당 지급이 끝난 날부터 6개월이 지나지 아니한 자는 참여 제외\n* 월평균 50만 원 이상 또는 총 300만 원 이상\n※ 6개월 산정 시점은 신청일 기준\n- ‘중기, 장기 프로그램’ 참여 후 종료된 자는 종료일(이수일 또는 중도탈락일)로부터 1년 경과 후 같은 프로그램 재참여 가능\n※ 단 중기, 장기 프로그램 중도탈락자 중 참여수당 지급받은 이력이 없는 자는 참여대상 요건 충족 시 참여 가능\n신청방법\n신청방법 - 신청절차, 심사 및 발표, 신청 사이트, 제출 서류\n신청절차\n신청방법\n① 고용24 홈페이지 접속하여 회원가입 후 구직회원 전환\n* 구직회원 전환 방법: 회원가입 후 [마이페이지] ▷ [이력서관리/구직신청] ▷ [워크넷 구직신청] ▷ [나의 구직신청정보 입력 후 구직신청하기]\n② 고용24 홈페이지 접속하여 로그인 후 ‘고용복지정책’ 탭 내 ‘청년도전지원사업’ 클릭 또는 아래 신청하기 클릭 → [고용24 청년도전 신청하기]\n③ 지원대상 및 청년센터 확인 후 신청 누르기\n④ 개인정보 입력 및 계좌번호 입력하기\n⑤ 개인정보동의 및 통장사본 등록\n⑥ 신청기관 선택하기\n심사 및 발표\n사업수행 지자체 운영기관 개별 신청 후, 운영기관 별 심사 연락\n신청 사이트\nhttps://www.work.go.kr/youngChallenge/index.do\n제출 서류\n기타\n기타 - 기타 정보, 주관 기관, 운영 기관, 참고사이트1, 참고사이트2\n기타 정보\n문의처: 거주지역의 25년 사업수행 지자체 운영기관을 검색 후 문의가능\n※사업수행자치단체 운영기관 목록확인: 사업관련 참고사이트2 참고\n주관 기관\n고용노동부\n운영 기관\n참고사이트 1\nhttp://www.moel.go.kr/policy/policyinfo/young/list18.do\n참고사이트 2\nhttps://www.work.go.kr/youngChallenge/retrieveCdjOperOrgPopup.do\n정보 변경 내역\n정보 변경 내역 표로 변경일자, 변경 내용으로 구성되어있음\n변경일자\t변경 내용\n2025.01.22\t최종 수정일\n2025.01.22\t최초 등록일",
      "operation_period": "사업 운영기간: 단기 프로그램 5주 이상, 중기 프로그램 15주 이상, 장기 프로그램 25주 이상",
      "application_period": "상시",
      "support_content": "ㅇ 사업운영기간: 5주 이상 ㅇ 참여수당: 1인당 50만원 ㅇ 이수 인센티브, 취업 인센티브: 없음 ㅇ 사업운영기간: 15주 이상 ㅇ 참여수당: 1인당 150만원(50만원x3회) ㅇ 이수 인센티브: 이수 시 20만원 ㅇ취업 인센티브: 이수 후 6개월 이내 취업하고 3개월 근속 시 50만원 ㅇ 사업운영기간: 25주 이상 ㅇ 참여수당: 1인당 250만원(50만원×5회) ㅇ 이수 인센티브: 이수 시 20만원, 취업관련 활동 시 30만원(국취Ⅰ유형은 국취참여수당으로 대체) ㅇ취업 인센티브: 이수 후 6개월 이내 취업하고 3개월 근속 시 50만원",
      "support_scale": null,
      "eligibility": {
        "income": {
          "description": "무관"
        },
        "region": ["전국"]
      },
      "application_info": {
        "application_url": "https://www.work.go.kr/youngChallenge/retrieveCdjOperOrgPopup.do",
        "managing_agency": "고용노동부",
        "operating_agency": "참고사이트 1"
      },
      "additional_info": {},
      "required_documents": [],
      "created_at": "2025-11-16T01:38:41.947188",
      "updated_at": "2025-11-16T01:38:41.947188"
    },
    {
      "id": 24,
      "policy_name": "청년안심주택 공급(매입)",
      "filename": "청년안심주택_공급매입_2025031600",
      "policy_number": "20250316005400210632",
      "region": "서울",
      "category": "주거",
      "deadline": "상시",
      "summary": "ㅇ 역세권(간선도로변)의 민간소유 토지를 체계적으로 개발(민간 주도+공공 지원)하여 쾌적하고 저렴한 주택을 공급함으로써 청년층의 주거안정을 도모하고 지역경제를 활성화하고자 함.",
      "full_text": "서울\n주거\n상시\n\n공유하기\n인쇄\n스크랩\n청년안심주택 공급(매입)\n최종 수정일2025년 3월 27일\n스크랩 수154\n조회수1875\n태그\n#공공임대주택\nㅇ 역세권(간선도로변)의 민간소유 토지를 체계적으로 개발(민간 주도+공공 지원)하여 쾌적하고 저렴한 주택을 공급함으로써 청년층의 주거안정을 도모하고 지역경제를 활성화하고자 함.\n\n한 눈에 보는 정책 요약\n한 눈에 보는 정책 요약 - 정책번호, 정책분야, 지원내용, 사업 운영 기간, 사업 신청기간, 지원 규모(명), 비고\n정책번호\n20250316005400210632\n정책분야\n주거\n지원내용\nㅇ (사업 근거)\n- 「민간임대주택에 관한 특별법」\n- 「서울특별시 청년안심주택 공급 지원에 관한 조례」\nㅇ (추진 경과)\n- ’16.03.25. 역세권 청년주택 공급계획 수립\n- ‘16.07.14. 「역세권 청년주택 공급 지원에 관한 조례」제정·시행\n- ‘16.08.22. 「역세권 청년주택 건립 및 운영기준」수립·시행\n- ‘19.11.26. 청년·신혼부부 주거비 지원계획 수립\n- `21.09.29. 「역세권 청년주택 건립 및 운영기준」개정(10차)\n- ’23.03.06. 역세권청년주택 혁신을 통한 ‘청년안심주택 추진방안’ 수립\n- ’23.05.22. 「청년안심주택 공급 지원에 관한 조례」개정\n- ’23.07, ’24.08. 「청년안심주택 건립 및 운영기준」개정(11차, 12차)\n- ’24.12.27. 「서울특별시 모두의 안심주택 건립 및 운영기준」제정\nㅇ (사업 기간)\n- 2016년 7월 ~ 2025년 12월\nㅇ (사업 대상)\n- 지원대상 : 청년 및 신혼부부\n- 연령기준 : 19~39세\n- 소득기준 : 도시근로자 월평균소득 100% ~120% 이하\nㅇ (사업 내용)\n- 역세권(간선도로변)에 민간이 임대주택을 건설하게 하고 일부를 청년안심주택(공공임대)으로 매입하여 청년ㆍ신혼부부에게 공급하는 사업\nㅇ (사업비) 79,662백만원 (국비 66,350 / 시비 13,312)\n사업 운영 기간\n2025년 1월 1일 ~ 2025년 12월 31일\n사업 신청기간\n상시\n지원 규모(명)\n0명\n신청자격\n신청자격 - 연령, 거주지역, 소득, 학력, 전공, 취업상태, 특화분야, 추가사항, 참여제한 대상\n연령\n만 19세~만 39세\n거주지역\n서울특별시 종로구, 서울특별시 중구, 서울특별시 용산구, 서울특별시 성동구, 서울특별시 광진구, 서울특별시 동대문구, 서울특별시 중랑구, 서울특별시 성북구, 서울특별시 강북구, 서울특별시 도봉구, 서울특별시 노원구, 서울특별시 은평구, 서울특별시 서대문구, 서울특별시 마포구, 서울특별시 양천구, 서울특별시 강서구, 서울특별시 구로구, 서울특별시 금천구, 서울특별시 영등포구, 서울특별시 동작구, 서울특별시 관악구, 서울특별시 서초구, 서울특별시 강남구, 서울특별시 송파구, 서울특별시 강동구\n소득\n도시근로자 월평균소득 100% ~120% 이하\n학력\n제한없음\n전공\n제한없음\n취업상태\n제한없음\n특화분야\n제한없음\n추가사항\n참여제한 대상\n신청방법\n신청방법 - 신청절차, 심사 및 발표, 신청 사이트, 제출 서류\n신청절차\n심사 및 발표\n신청 사이트\n제출 서류\n기타\n기타 - 기타 정보, 주관 기관, 운영 기관, 참고사이트1, 참고사이트2\n기타 정보\n주관 기관\n건축기획관\n운영 기관\n참고사이트 1\n참고사이트 2\n정보 변경 내역\n정보 변경 내역 표로 변경일자, 변경 내용으로 구성되어있음\n변경일자\t변경 내용\n2025.03.27\t최종 수정일\n2025.03.16\t최초 등록일",
      "operation_period": "2025년 1월 1일 ~ 2025년 12월 31일",
      "application_period": "상시",
      "support_content": "ㅇ (사업 근거) - 「민간임대주택에 관한 특별법」 - 「서울특별시 청년안심주택 공급 지원에 관한 조례」 ㅇ (추진 경과) - ’16.03.25. 역세권 청년주택 공급계획 수립 - ‘16.07.14. 「역세권 청년주택 공급 지원에 관한 조례」제정·시행 - ‘16.08.22. 「역세권 청년주택 건립 및 운영기준」수립·시행 - ‘19.11.26. 청년·신혼부부 주거비 지원계획 수립 - `21.09.29. 「역세권 청년주택 건립 및 운영기준」개정(10차) - ’23.03.06. 역세권청년주택 혁신을 통한 ‘청년안심주택 추진방안’ 수립 - ’23.05.22. 「청년안심주택 공급 지원에 관한 조례」개정 - ’23.07, ’24.08. 「청년안심주택 건립 및 운영기준」개정(11차, 12차) - ’24.12.27. 「서울특별시 모두의 안심주택 건립 및 운영기준」제정 ㅇ (사업 기간) - 2016년 7월 ~ 2025년 12월 ㅇ (사업 대상) - 지원대상 : 청년 및 신혼부부 - 연령기준 : 19~39세 - 소득기준 : 도시근로자 월평균소득 100% ~120% 이하 ㅇ (사업 내용) - 역세권(간선도로변)에 민간이 임대주택을 건설하게 하고 일부를 청년안심주택(공공임대)으로 매입하여 청년ㆍ신혼부부에게 공급하는 사업 ㅇ (사업비) 79,662백만원 (국비 66,350 / 시비 13,312)",
      "support_scale": null,
      "eligibility": {
        "age": {
          "max": 39,
          "min": 19,
          "description": "만 19세~만 39세"
        },
        "income": {
          "description": "도시근로자 월평균소득 100% ~120% 이하"
        },
        "region": [
          "서울특별시 종로구, 서울특별시 중구, 서울특별시 용산구, 서울특별시 성동구, 서울특별시 광진구, 서울특별시 동대문구, 서울특별시 중랑구, 서울특별시 성북구, 서울특별시 강북구, 서울특별시 도봉구, 서울특별시 노원구, 서울특별시 은평구, 서울특별시 서대문구, 서울특별시 마포구, 서울특별시 양천구, 서울특별시 강서구, 서울특별시 구로구, 서울특별시 금천구, 서울특별시 영등포구, 서울특별시 동작구, 서울특별시 관악구, 서울특별시 서초구, 서울특별시 강남구, 서울특별시 송파구, 서울특별시 강동구"
        ]
      },
      "application_info": {
        "managing_agency": "건축기획관",
        "operating_agency": "참고사이트 1"
      },
      "additional_info": {},
      "required_documents": [],
      "created_at": "2025-11-16T01:38:41.951806",
      "updated_at": "2025-11-16T01:38:41.951806"
    },
    {
      "id": 25,
      "policy_name": "청년안심주택 공급활성화(임차보증금 무이자지원)",
      "filename": "청년안심주택_공급활성화임차보증금_무이자지원_2025031600",
      "policy_number": "20250316005400210633",
      "region": "서울",
      "category": "주거",
      "deadline": "상시",
      "summary": "ㅇ 높은 주거비 부담 등에 시달리는 청년․신혼부부의 안정적인 주거환경 확보를 위해 청년안심주택 입주자에 대하여 주거비를 지원",
      "full_text": "서울\n주거\n상시\n\n공유하기\n인쇄\n스크랩\n청년안심주택 공급활성화(임차보증금 무이자지원)\n최종 수정일2025년 5월 26일\n스크랩 수211\n조회수12665\n태그\n#금리혜택\nㅇ 높은 주거비 부담 등에 시달리는 청년․신혼부부의 안정적인 주거환경 확보를 위해 청년안심주택 입주자에 대하여 주거비를 지원\n\n한 눈에 보는 정책 요약\n한 눈에 보는 정책 요약 - 정책번호, 정책분야, 지원내용, 사업 운영 기간, 사업 신청기간, 지원 규모(명), 비고\n정책번호\n20250316005400210633\n정책분야\n주거\n지원내용\nㅇ (사업 근거)\n- 「서울시 보증금지원형 장기안심주택 업무처리 지침」\nㅇ (추진 경과)\n- ‘16.03.25. 역세권 청년주택 공급계획 수립\n- ‘19.11.26. 청년·신혼부부 주거비 지원계획 수립\n- `19.12.09 역세권 청년주택 혁신방안\nㅇ (사업 기간)\n- 2021년 1월 ~\nㅇ (사업 대상)\n- 지원대상 : 청년안심주택, 민간임대주택 입주(예정)자\n- 연령기준 : 19~39세\n- 소득 : 전년도 도시근로자 가구당 월평균소득의 100%(신혼부부 120%) 이하\n- 자산 : 청년 2억 7,300만원 이하 / 신혼부부 3억 4,500만원 이하\nㅇ (사업 내용)\n- 임차보증금 무이자 지원\n· 1억원 초과시 보증금의 30%, 1억 이하는 보증금의 50%\n· 최대 지원금액 청년 4,500만원 / 신혼부부 6,000만원\nㅇ (사업 주체)\n- 서울시, SH공사\nㅇ (사업 추진절차)\n- 신청인이 임대차 계약 체결 후 약정서 작성 및 구비서류 제출\n- 소득심사 등을 거쳐 확정시 지원금액 지급하고 보증보험 가입\n사업 운영 기간\n2025년 1월 1일 ~ 2025년 12월 31일\n사업 신청기간\n상시\n지원 규모(명)\n5192명\n신청자격\n신청자격 - 연령, 거주지역, 소득, 학력, 전공, 취업상태, 특화분야, 추가사항, 참여제한 대상\n연령\n만 19세~만 39세\n거주지역\n서울특별시 종로구, 서울특별시 중구, 서울특별시 용산구, 서울특별시 성동구, 서울특별시 광진구, 서울특별시 동대문구, 서울특별시 중랑구, 서울특별시 성북구, 서울특별시 강북구, 서울특별시 도봉구, 서울특별시 노원구, 서울특별시 은평구, 서울특별시 서대문구, 서울특별시 마포구, 서울특별시 양천구, 서울특별시 강서구, 서울특별시 구로구, 서울특별시 금천구, 서울특별시 영등포구, 서울특별시 동작구, 서울특별시 관악구, 서울특별시 서초구, 서울특별시 강남구, 서울특별시 송파구, 서울특별시 강동구\n소득\n전년도 도시근로자 가구당 월평균소득의 100%(신혼부부 120%) 이하\n학력\n제한없음\n전공\n제한없음\n취업상태\n제한없음\n특화분야\n제한없음\n추가사항\n참여제한 대상\n신청방법\n신청방법 - 신청절차, 심사 및 발표, 신청 사이트, 제출 서류\n신청절차\n심사 및 발표\n신청 사이트\n제출 서류\n기타\n기타 - 기타 정보, 주관 기관, 운영 기관, 참고사이트1, 참고사이트2\n기타 정보\n주관 기관\n건축기획관\n운영 기관\n참고사이트 1\n참고사이트 2\n정보 변경 내역\n정보 변경 내역 표로 변경일자, 변경 내용으로 구성되어있음\n변경일자\t변경 내용\n2025.05.26\t최종 수정일\n2025.03.16\t최초 등록일",
      "operation_period": "2025년 1월 1일 ~ 2025년 12월 31일",
      "application_period": "상시",
      "support_content": "ㅇ (사업 근거) - 「서울시 보증금지원형 장기안심주택 업무처리 지침」 ㅇ (추진 경과) - ‘16.03.25. 역세권 청년주택 공급계획 수립 - ‘19.11.26. 청년·신혼부부 주거비 지원계획 수립 - `19.12.09 역세권 청년주택 혁신방안 ㅇ (사업 기간) - 2021년 1월 ~ ㅇ (사업 대상) - 지원대상 : 청년안심주택, 민간임대주택 입주(예정)자 - 연령기준 : 19~39세 - 소득 : 전년도 도시근로자 가구당 월평균소득의 100%(신혼부부 120%) 이하 - 자산 : 청년 2억 7,300만원 이하 / 신혼부부 3억 4,500만원 이하 ㅇ (사업 내용) - 임차보증금 무이자 지원 · 1억원 초과시 보증금의 30%, 1억 이하는 보증금의 50% · 최대 지원금액 청년 4,500만원 / 신혼부부 6,000만원 ㅇ (사업 주체) - 서울시, SH공사 ㅇ (사업 추진절차) - 신청인이 임대차 계약 체결 후 약정서 작성 및 구비서류 제출 - 소득심사 등을 거쳐 확정시 지원금액 지급하고 보증보험 가입",
      "support_scale": null,
      "eligibility": {
        "age": {
          "max": 39,
          "min": 19,
          "description": "만 19세~만 39세"
        },
        "income": {
          "description": "전년도 도시근로자 가구당 월평균소득의 100%(신혼부부 120%) 이하"
        },
        "region": [
          "서울특별시 종로구, 서울특별시 중구, 서울특별시 용산구, 서울특별시 성동구, 서울특별시 광진구, 서울특별시 동대문구, 서울특별시 중랑구, 서울특별시 성북구, 서울특별시 강북구, 서울특별시 도봉구, 서울특별시 노원구, 서울특별시 은평구, 서울특별시 서대문구, 서울특별시 마포구, 서울특별시 양천구, 서울특별시 강서구, 서울특별시 구로구, 서울특별시 금천구, 서울특별시 영등포구, 서울특별시 동작구, 서울특별시 관악구, 서울특별시 서초구, 서울특별시 강남구, 서울특별시 송파구, 서울특별시 강동구"
        ]
      },
      "application_info": {
        "managing_agency": "건축기획관",
        "operating_agency": "참고사이트 1"
      },
      "additional_info": {},
      "required_documents": [],
      "created_at": "2025-11-16T01:38:41.954350",
      "updated_at": "2025-11-16T01:38:41.954350"
    },
    {
      "id": 26,
      "policy_name": "청년일자리 도약장려금",
      "filename": "청년일자리_도약장려금_2025012300",
      "policy_number": "20250123005400110390",
      "region": "전국",
      "category": "일자리",
      "deadline": "신청마감 D-49",
      "summary": "기업의 청년고용 확대를 지원하고, 취업애로 청년의 취업을 촉진함으로써, 청년고용 활성화를 목적으로 하는 정책 ㅇ (유형Ⅰ) 5인 이상 중소기업에서 취업애로청년을 정규직으로 채용하고 6개월 이상 고용유지시 기업지원금 지급 ㅇ (유형Ⅱ) 빈일자리 업종 중소기업에서 청년을 정규직으로 채용 후 6개월 이상 고용유지시 기업지원금 지급하고, 해당 기업에서 18개월 이상 재직한 청년에게 청년장기근속인센티브 지급",
      "full_text": "전국\n일자리\n신청마감 D-49\n\n공유하기\n인쇄\n스크랩\n청년일자리 도약장려금\n최종 수정일2025년 1월 23일\n스크랩 수415\n조회수117557\n태그\n#장기미취업청년\n기업의 청년고용 확대를 지원하고, 취업애로 청년의 취업을 촉진함으로써, 청년고용 활성화를 목적으로 하는 정책 ㅇ (유형Ⅰ) 5인 이상 중소기업에서 취업애로청년을 정규직으로 채용하고 6개월 이상 고용유지시 기업지원금 지급 ㅇ (유형Ⅱ) 빈일자리 업종 중소기업에서 청년을 정규직으로 채용 후 6개월 이상 고용유지시 기업지원금 지급하고, 해당 기업에서 18개월 이상 재직한 청년에게 청년장기근속인센티브 지급\n\n한 눈에 보는 정책 요약\n한 눈에 보는 정책 요약 - 정책번호, 정책분야, 지원내용, 사업 운영 기간, 사업 신청기간, 지원 규모(명), 비고\n정책번호\n20250123005400110390\n정책분야\n일자리\n지원내용\nㅇ (유형Ⅰ) 5인 이상 우선지원대상기업에서 취업애로청년을 정규직으로 채용시 1년간 최대 720만원 지원\n* 취업애로청년: 만 15~34세의 ▴4개월 이상 실업, ▴고졸 이하 청년 등\nㅇ(유형Ⅱ) 5인 이상의 제조업 등 빈일자리 업종 중소기업에서 청년을 정규직으로 채용시 1년간 최대 720만원 지원 및 해당 기업에 취업 후 18개월 이상 재직한 청년 근로자에게 최대 480만원 지원(18.24개월차 각 240만원)\n사업 운영 기간\n2025년 1월 1일 ~ 2025년 12월 31일\n사업 신청기간\n2025년 1월 1일 ~ 2025년 12월 31일\n지원 규모(명)\n제한없음\n신청자격\n신청자격 - 연령, 거주지역, 소득, 학력, 전공, 취업상태, 특화분야, 추가사항, 참여제한 대상\n연령\n만 15세~만 34세\n거주지역\n전국\n소득\n(기업)매출액 기준 (청년)해당없음\n학력\n제한없음\n전공\n제한없음\n취업상태\n재직자\n특화분야\n제한없음\n추가사항\n① 근로조건\n- 정규직 채용 후 6개월 이상 고용유지\n* 계약직 채용시 채용일로부터 3개월 이내 정규직 전환\n- 주 30시간 이상 근로 및 최저임금 이상 지급\n- 고용보험 가입 필수\n② 채용요건\n- ‘25.1.1. 이후 채용된 청년\n- 원칙적으로 사업 참여신청 후 채용된 청년을 지원\n* 단, ’25.1.1. 이후 채용된 청년 중 채용일로부터 3개월 이내에 참여신청한 경우 지원 가능\n③ 인위적 감원 방지\n- 사업참여 신청 직전 3개월부터 청년의 지원금 지급기간까지 인위적 감원 금지\n* 단, 예산 사정에 따라 참여신청 및 지원대상 선정은 조기에 마감될 수 있으며, 먼저 채용하여 사업을 신청한 기업에 우선 지원\n* 구체적인 요건 및 자격은 운영지침 반드시 확인필요\n참여제한 대상\n사업주의 배우자, 직계 존비속, 외국인, 중앙부처 또는 지방자치단체로부터 다른 인건비 지원을 받는 청년, 채용일 기준 고등학교 또는 대학교재학 중인자 등은 지원 제외\n* 구체적인 요건 및 자격은 운영지침 반드시 확인필요\n신청방법\n신청방법 - 신청절차, 심사 및 발표, 신청 사이트, 제출 서류\n신청절차\n신청방법 및 지원절차\n(참여신청) 기업이 운영기관에 채용계획 제출(전산시스템 활용)-> 운영기관의 검토 및 승인-> 운영기관-기업 간 지원협약 체결\n(채용) 기업은 청년 채용 후 운영기관에 채용명단 제출, 6개월 간 고용 유지하며 임금지급\n(장려금 신청) 최소 근속기간 도래 후 운영기관에 장려금 신청\nㅇ (유형Ⅰ_기업지원금) 6개월 이상 고용유지시 기업지원금 신청\nㅇ (유형Ⅱ_기업지원금) 6개월 이상 고용유지시 기업지원금 신청\nㅇ (유형Ⅱ_청년인센티브)186개월 이상 근속시 청년 장기근속인센티브 신청\n(지원금 지급) 운영기관은 사전 심사 후 고용센터에 지급 검토보고서 제출, 고용센터에서 최종 심사 후 기업에 지원금 지급\n심사 및 발표\n신청 사이트\nhttps://www.work24.go.kr\n제출 서류\n기타\n기타 - 기타 정보, 주관 기관, 운영 기관, 참고사이트1, 참고사이트2\n기타 정보\n주관 기관\n고용노동부\n운영 기관\n참고사이트 1\nhttps://www.work24.go.kr\n참고사이트 2\n정보 변경 내역\n정보 변경 내역 표로 변경일자, 변경 내용으로 구성되어있음\n변경일자\t변경 내용\n2025.01.23\t최종 수정일\n2025.01.23\t최초 등록일",
      "operation_period": "2025년 1월 1일 ~ 2025년 12월 31일",
      "application_period": "2025년 1월 1일 ~ 2025년 12월 31일",
      "support_content": "ㅇ (유형Ⅰ) 5인 이상 우선지원대상기업에서 취업애로청년을 정규직으로 채용시 1년간 최대 720만원 지원 * 취업애로청년: 만 15~34세의 ▴4개월 이상 실업, ▴고졸 이하 청년 등 ㅇ(유형Ⅱ) 5인 이상의 제조업 등 빈일자리 업종 중소기업에서 청년을 정규직으로 채용시 1년간 최대 720만원 지원 및 해당 기업에 취업 후 18개월 이상 재직한 청년 근로자에게 최대 480만원 지원(18.24개월차 각 240만원)",
      "support_scale": null,
      "eligibility": {
        "age": {
          "max": 34,
          "min": 15,
          "description": "만 15세~만 34세"
        },
        "income": {
          "description": "(기업)매출액 기준 (청년)해당없음"
        },
        "region": ["전국"]
      },
      "application_info": {
        "application_url": "https://www.work24.go.kr",
        "managing_agency": "고용노동부",
        "operating_agency": "참고사이트 1"
      },
      "additional_info": {},
      "required_documents": [],
      "created_at": "2025-11-16T01:38:41.956859",
      "updated_at": "2025-11-16T01:38:41.956859"
    },
    {
      "id": 27,
      "policy_name": "청년주택드림청약통장",
      "filename": "청년주택드림청약통장_2025022600",
      "policy_number": "20250226005400110565",
      "region": "전국",
      "category": "주거",
      "deadline": "상시",
      "summary": "무주택 청년의 주택구입과 자산형성을 지원",
      "full_text": "전국\n주거\n상시\n\n공유하기\n인쇄\n스크랩\n청년주택드림청약통장\n최종 수정일2025년 2월 27일\n스크랩 수651\n조회수19907\n태그\n#금리혜택\n무주택 청년의 주택구입과 자산형성을 지원\n\n한 눈에 보는 정책 요약\n한 눈에 보는 정책 요약 - 정책번호, 정책분야, 지원내용, 사업 운영 기간, 사업 신청기간, 지원 규모(명), 비고\n정책번호\n20250226005400110565\n정책분야\n주거\n지원내용\n□ 이자율: 최대 4.5%\n□ 소득기준: 연 5,000만원(직전년도 신고소득이 있는 자 기준), 무주택자\n□ 납입한도: 월 100만원\n□ 납입금액의 40%까지 소득공제\n□ 주택청약에 당첨된 경우 청년주택드림 대출 연계\nㅇ 청년주택드림 청약통장 1년 이상 가입\nㅇ 1,000만원 이상 납입\nㅇ 당첨 시 분양가 80%까지 대출\nㅇ 금리 최저 연 2.2%(만기, 소득별 차등) 최장 40년까지 지원(고정금리)\nㅇ 6억 이하, 전용면적 85제곱미터 이하 주택\nㅇ 생애주기별 금리 인하: 결혼 0.1%p 인하, 출산: 0.5%p 인하, 다자녀: 0.2%p 인하\n사업 운영 기간\n상시\n사업 신청기간\n상시\n지원 규모(명)\n제한없음\n신청자격\n신청자격 - 연령, 거주지역, 소득, 학력, 전공, 취업상태, 특화분야, 추가사항, 참여제한 대상\n연령\n만 19세~만 34세\n거주지역\n전국\n소득\n연소득 0만원 이상 ~ 5000만원 이하\n학력\n제한없음\n전공\n제한없음\n취업상태\n제한없음\n특화분야\n제한없음\n추가사항\n□ 소득기준: 연 5,000만원(직전년도 신고소득이 있는 자 기준), 무주택자\n참여제한 대상\n신청방법\n신청방법 - 신청절차, 심사 및 발표, 신청 사이트, 제출 서류\n신청절차\n심사 및 발표\n신청 사이트\n제출 서류\n기타\n기타 - 기타 정보, 주관 기관, 운영 기관, 참고사이트1, 참고사이트2\n기타 정보\n□ 업무 취급 은행\n○ 우리은행 : 1599-0800\n○ KB 국민은행 : 1599-1771\n○ IBK 기업은행 : 1566-2566\n○ NHBank : 1588-2100\n○ 신한은행 : 1599-8000\n○ 하나은행 : 1599-1111\n○ 대구은행 : 1566-5050\n○ 부산은행 : 1800-1333\n○ 경남은행 : 1600-8585\n주관 기관\n국토교통부\n운영 기관\n국토교통부\n참고사이트 1\nhttps://nhuf.molit.go.kr/FP/FP07/FP0701/FP07010301.jsp\n참고사이트 2\nhttps://www.korea.kr/news/policyNewsView.do?newsId=148926066\n정보 변경 내역\n정보 변경 내역 표로 변경일자, 변경 내용으로 구성되어있음\n변경일자\t변경 내용\n2025.02.27\t최종 수정일\n2025.02.26\t최초 등록일",
      "operation_period": "상시",
      "application_period": "상시",
      "support_content": "ㅇ 청년주택드림 청약통장 1년 이상 가입 ㅇ 1,000만원 이상 납입 ㅇ 당첨 시 분양가 80%까지 대출 ㅇ 금리 최저 연 2.2%(만기, 소득별 차등) 최장 40년까지 지원(고정금리) ㅇ 6억 이하, 전용면적 85제곱미터 이하 주택 ㅇ 생애주기별 금리 인하: 결혼 0.1%p 인하, 출산: 0.5%p 인하, 다자녀: 0.2%p 인하",
      "support_scale": null,
      "eligibility": {
        "age": {
          "max": 34,
          "min": 19,
          "description": "만 19세~만 34세"
        },
        "income": {
          "description": "연소득 0만원 이상 ~ 5000만원 이하"
        },
        "region": ["전국"]
      },
      "application_info": {
        "application_url": "https://www.korea.kr/news/policyNewsView.do?newsId=148926066",
        "managing_agency": "국토교통부",
        "operating_agency": "국토교통부"
      },
      "additional_info": {},
      "required_documents": [],
      "created_at": "2025-11-16T01:38:41.958811",
      "updated_at": "2025-11-16T01:38:41.958811"
    },
    {
      "id": 28,
      "policy_name": "취업지원대상자 취업능력개발비용 지원(국가보훈부)",
      "filename": "취업지원대상자_취업능력개발비용_지원국가보훈부_2025011300",
      "policy_number": "20250113005400110180",
      "region": "전국",
      "category": "일자리",
      "deadline": "상시",
      "summary": "국가보훈대상자 중 '취업지원 대상자의 취업역량 향이상'을 위한 취업수강료 지원",
      "full_text": "전국\n일자리\n상시\n\n공유하기\n인쇄\n스크랩\n취업지원대상자 취업능력개발비용 지원(국가보훈부)\n최종 수정일2025년 1월 13일\n스크랩 수121\n조회수2717\n태그\n#장기미취업청년\n국가보훈대상자 중 '취업지원 대상자의 취업역량 향이상'을 위한 취업수강료 지원\n\n한 눈에 보는 정책 요약\n한 눈에 보는 정책 요약 - 정책번호, 정책분야, 지원내용, 사업 운영 기간, 사업 신청기간, 지원 규모(명), 비고\n정책번호\n20250113005400110180\n정책분야\n일자리\n지원내용\n1. 1인당 지원 한도액(연간 지원한도액)\n- 유공자 본인: 총 300만원(연간 150만원)\n- 유가족: 총 150만원(연간 75만원)\n* 단, 취업지원대상자 본인이 제대군인과 국가유공자 자격의 중복으로 제대군인 직업능력개발교육비 지원을 받은 경우 그 차액에 대해 지원(중복 수혜 불가)\n\n2. 지원비율: 취업수강료 실부담액의 70% 지원\n사업 운영 기간\n예산소진시 까지\n사업 신청기간\n상시\n지원 규모(명)\n0명\n신청자격\n신청자격 - 연령, 거주지역, 소득, 학력, 전공, 취업상태, 특화분야, 추가사항, 참여제한 대상\n연령\n만 18세~만 74세\n거주지역\n전국\n소득\n무관\n학력\n고졸 미만, 고졸 예정, 고교 졸업, 대졸 예정, 대학 졸업, 석·박사, 기타\n전공\n제한없음\n취업상태\n미취업자\n특화분야\n기타\n추가사항\n참여제한 대상\n1. 제대군인\n2. 법정취업자, 보훈특별고용통지서가 발급된 자, 가점 또는 일반직공무원 등 특별채용 합격자로 결정된 자\n3. (수강시작일 기준) 75세 이상자, 단, 지원연령 상한이 없는 과정은 지원 가능\n4. 18세 미만자\n신청방법\n신청방법 - 신청절차, 심사 및 발표, 신청 사이트, 제출 서류\n신청절차\n1. 신청방법: 관할보훈(지)청 방문 또는 취업정보시스템(job.mpva.go.kr) 이용\n2. 신청기간: 수강시작일 부터 수강 종료일 후 12개월 이내\n* 단, 해당 과정의 수강진도율이 80% 이상인 때 부터 비용 지급 가능\n3. 제출서류: 하단 참고\n심사 및 발표\n신청 사이트\n제출 서류\n1. 취업능력개발 비용 지원 신청 및 확인서(개인정보 이용 및 제공 사전 동의서 포함)\n2. 수강료 영수증\n3. 서약서\n4. 수강완료 및 훈련비 지원여부 사실확인서\n5. 응시확인서류(시험일이 경과한 응시(수험)표, 성적표, 합격증 등)\n기타\n기타 - 기타 정보, 주관 기관, 운영 기관, 참고사이트1, 참고사이트2\n기타 정보\n1. 취업능력개발비용 지원이 가능한 수강과목(과정)은 '대상자의 자격 또는 연령 등'에 따라 다를 수 있음\n2. 취업수강료의 지급 신청 시에 응시확인서류를 제출하지 않은 경우 지급 대상 제외\n* 응시확인서류(예시): 시험일이 경과한 응시(수험)표, 합격증, 성적표 등\n주관 기관\n국가보훈부\n운영 기관\n참고사이트 1\nhttps://job.mpva.go.kr/\n참고사이트 2\n정보 변경 내역\n정보 변경 내역 표로 변경일자, 변경 내용으로 구성되어있음\n변경일자\t변경 내용\n2025.01.13\t최종 수정일\n2025.01.13\t최초 등록일",
      "operation_period": "예산소진시 까지",
      "application_period": "상시",
      "support_content": "1. 1인당 지원 한도액(연간 지원한도액) - 유공자 본인: 총 300만원(연간 150만원) - 유가족: 총 150만원(연간 75만원) * 단, 취업지원대상자 본인이 제대군인과 국가유공자 자격의 중복으로 제대군인 직업능력개발교육비 지원을 받은 경우 그 차액에 대해 지원(중복 수혜 불가) 2. 지원비율: 취업수강료 실부담액의 70% 지원",
      "support_scale": null,
      "eligibility": {
        "age": {
          "max": 74,
          "min": 18,
          "description": "만 18세~만 74세"
        },
        "income": {
          "description": "무관"
        },
        "region": ["전국"]
      },
      "application_info": {
        "application_url": "https://job.mpva.go.kr/",
        "managing_agency": "국가보훈부",
        "operating_agency": "참고사이트 1"
      },
      "additional_info": {},
      "required_documents": [],
      "created_at": "2025-11-16T01:38:41.960167",
      "updated_at": "2025-11-16T01:38:41.960167"
    }
  ]
}
